{
    "each": "/ˈiːt‍ʃ/",
    "eager": "/ˈiːɡɐ/",
    "eagerly": "/ˈiːɡəli/",
    "eagerness": "/ˈiːɡənəs/",
    "eagle": "/ˈiːɡə‍l/",
    "eagles": "/ˈiːɡə‍lz/",
    "eaglet": "/ˈiːɡlət/",
    "earache": "/ˈi‍əɹe‍ɪk/",
    "eardrops": "/ˈi‍ədɹɒps/",
    "eardrum": "/ˈi‍ədɹəm/",
    "eardrums": "/ˈi‍ədɹəmz/",
    "eared": "/ˈi‍əd/",
    "earflaps": "/ˈi‍əflæps/",
    "earful": "/ˈi‍əfə‍l/",
    "ear": "/ˈi‍ə/",
    "earing": "/ˈi‍əɹɪŋ/",
    "earldom": "/ˈɜːldəm/",
    "earldoms": "/ˈɜːldəmz/",
    "earlier": "/ˈɜːlɪɐ/",
    "earliest": "/ˈɜːlɪəst/",
    "earliness": "/ˈɜːlɪnəs/",
    "earl": "/ˈɜːl/",
    "earlobe": "/ˈi‍ələ‍ʊb/",
    "earlobes": "/ˈi‍ələ‍ʊbz/",
    "earls": "/ˈɜːlz/",
    "early": "/ˈɜːli/",
    "earmarked": "/ˈi‍əmɑːkt/",
    "earmark": "/ˈi‍əmɑːk/",
    "earmarking": "/ˈi‍əmɑːkɪŋ/",
    "earmarks": "/ˈi‍əmɑːks/",
    "earmuffs": "/ˈi‍əmʌfs/",
    "earned": "/ˈɜːnd/",
    "earner": "/ˈɜːnɐ/",
    "earners": "/ˈɜːnəz/",
    "earnestly": "/ˈɜːnəstli/",
    "earnestness": "/ˈɜːnəstnəs/",
    "earnest": "/ˈɜːnəst/",
    "earning": "/ˈɜːnɪŋ/",
    "earnings": "/ˈɜːnɪŋz/",
    "earn": "/ˈɜːn/",
    "earns": "/ˈɜːnz/",
    "earphone": "/ˈi‍əfə‍ʊn/",
    "earphones": "/ˈi‍əfə‍ʊnz/",
    "earpiece": "/ˈi‍əpiːs/",
    "earpieces": "/ˈi‍əpiːsɪz/",
    "earplug": "/ˈi‍əplʌɡ/",
    "earplugs": "/ˈi‍əplʌɡz/",
    "earring": "/ˈi‍əɹɪŋ/",
    "earrings": "/ˈi‍əɹɪŋz/",
    "earshot": "/ˈi‍əʃɒt/",
    "ears": "/ˈi‍əz/",
    "earthbound": "/ˈɜːθba‍ʊnd/",
    "earthed": "/ˈɜːθd/",
    "earthen": "/ˈɜːðən/",
    "earthenware": "/ˈɜːθənwˌe‍ə/",
    "earthier": "/ˈɜːθɪɐ/",
    "earthiness": "/ˈɜːθɪnəs/",
    "earthing": "/ˈɜːθɪŋ/",
    "earthlight": "/ˈɜːθla‍ɪt/",
    "earthliness": "/ˈɜːθlinəs/",
    "earthlings": "/ˈɜːθlɪŋz/",
    "earthling": "/ˈɜːθlɪŋ/",
    "earthly": "/ˈɜːθli/",
    "earthman": "/ˈɜːθmən/",
    "earthquakes": "/ˈɜːθkwe‍ɪks/",
    "earthquake": "/ˈɜːθkwe‍ɪk/",
    "earthshine": "/ˈɜːθʃa‍ɪn/",
    "earths": "/ˈɜːθs/",
    "earthwards": "/ˈɜːθwədz/",
    "earthworks": "/ˈɜːθwɜːks/",
    "earthwork": "/ˈɜːθwɜːk/",
    "earthworms": "/ˈɜːθwɜːmz/",
    "earthworm": "/ˈɜːθwɜːm/",
    "earthy": "/ˈɜːθi/",
    "earth": "/ˈɜːθ/",
    "earwax": "/ˈi‍əwæks/",
    "earwig": "/ˈi‍əwɪɡ/",
    "earwigs": "/ˈi‍əwɪɡz/",
    "eased": "/ˈiːzd/",
    "easeful": "/ˈiːzfə‍l/",
    "ease": "/ˈiːz/",
    "easel": "/ˈiːzə‍l/",
    "easels": "/ˈiːzə‍lz/",
    "easement": "/ˈiːzmənt/",
    "eases": "/ˈiːzɪz/",
    "easier": "/ˈiːzɪɐ/",
    "easiest": "/ˈiːzɪəst/",
    "easily": "/ˈiːzɪli/",
    "easiness": "/ˈiːzɪnəs/",
    "easing": "/ˈiːzɪŋ/",
    "eastbound": "/ˈiːstba‍ʊnd/",
    "easterly": "/ˈiːstəli/",
    "easterner": "/ˈiːstənɐ/",
    "easterners": "/ˈiːstənəz/",
    "eastern": "/ˈiːstən/",
    "easternmost": "/ˈiːstənmˌə‍ʊst/",
    "east": "/ˈiːst/",
    "eastward": "/ˈiːstwəd/",
    "eastwards": "/ˈiːstwədz/",
    "easygoing": "/iːzˈɪɡə‍ʊɪŋ/",
    "easy": "/ˈiːzi/",
    "eatable": "/ˈiːtəbə‍l/",
    "eaten": "/ˈiːtən/",
    "eateries": "/ˈiːtəɹiz/",
    "eater": "/ˈiːtɐ/",
    "eaters": "/ˈiːtəz/",
    "eatery": "/ˈiːtəɹi/",
    "eating": "/ˈiːtɪŋ/",
    "eat": "/ˈiːt/",
    "eats": "/ˈiːts/",
    "eau": "/ˈə‍ʊ/",
    "eave": "/ˈiːv/",
    "eavesdrop": "/ˈiːvzdɹɒp/",
    "eavesdropped": "/ˈiːvzdɹɒpt/",
    "eavesdropper": "/ˈiːvzdɹɒpɐ/",
    "eavesdroppers": "/ˈiːvzdɹɒpəz/",
    "eavesdropping": "/ˈiːvzdɹɒpɪŋ/",
    "eavesdrops": "/ˈiːvzdɹɒps/",
    "eaves": "/ˈiːvz/",
    "ebb": "/ˈɛb/",
    "ebbed": "/ˈɛbd/",
    "ebbing": "/ˈɛbɪŋ/",
    "ebbs": "/ˈɛbz/",
    "ebonies": "/ˈɛbənɪz/",
    "ebonised": "/ˈɛbənˌa‍ɪzd/",
    "ebony": "/ˈɛbəni/",
    "ebullience": "/ɪbˈʊli‍əns/",
    "ebullient": "/ɪbˈʊli‍ənt/",
    "eccentrically": "/ɛksˈɛntɹɪkli/",
    "eccentric": "/ɛksˈɛntɹɪk/",
    "eccentricities": "/ˌɛksɪntɹˈɪsɪtiz/",
    "eccentricity": "/ˌɛksɪntɹˈɪsɪti/",
    "eccentrics": "/ɛksˈɛntɹɪks/",
    "ecclesia": "/ɪklˈiːzi‍ə/",
    "ecclesiastical": "/ɪklˌiːzɪˈæstɪkə‍l/",
    "ecclesiastic": "/ɪklˌiːzɪˈæstɪk/",
    "ecclesiastics": "/ɪklˌiːzɪˈæstɪks/",
    "echelon": "/ˈɛʃəlˌɒn/",
    "echelons": "/ˈɛʃəlˌɒnz/",
    "echidna": "/ˈɛt‍ʃɪdnɐ/",
    "echidnas": "/ˈɛt‍ʃɪdnəz/",
    "echinacea": "/ˌɛt‍ʃa‍ɪnˈe‍ɪsi‍ə/",
    "echinoderm": "/ˈɛt‍ʃɪnˌə‍ʊdəm/",
    "echinoderms": "/ˈɛt‍ʃɪnˌə‍ʊdəmz/",
    "echoed": "/ˈɛkə‍ʊd/",
    "echo": "/ˈɛkə‍ʊ/",
    "echoes": "/ˈɛkə‍ʊz/",
    "echoing": "/ˈɛkə‍ʊɪŋ/",
    "echolalia": "/ˌɛkəlˈe‍ɪli‍ə/",
    "echolocate": "/ˈɛkələ‍ʊkˌe‍ɪt/",
    "echolocation": "/ˌɛkələ‍ʊkˈe‍ɪʃən/",
    "echopraxia": "/ˌɛkəpɹˈe‍ɪksi‍ə/",
    "echos": "/ˈɛkə‍ʊz/",
    "echt": "/ˈɛt‍ʃt/",
    "eclampsia": "/ɪklˈæmpsi‍ə/",
    "eclecticism": "/ɪklˈɛktɪsˌɪzəm/",
    "eclectic": "/ɪklˈɛktɪk/",
    "eclipsed": "/ɪklˈɪpsd/",
    "eclipse": "/ɪklˈɪps/",
    "eclipses": "/ɪklˈɪpsɪz/",
    "eclipsing": "/ɪklˈɪpsɪŋ/",
    "ecliptic": "/ɪklˈɪptɪk/",
    "ecological": "/ˌɛkəlˈɒd‍ʒɪkə‍l/",
    "ecologically": "/ˌɛkəlˈɒd‍ʒɪkli/",
    "ecologist": "/ɛkˈɒləd‍ʒˌɪst/",
    "ecologists": "/ɛkˈɒləd‍ʒˌɪsts/",
    "ecology": "/ɛkˈɒləd‍ʒi/",
    "economical": "/ˌiːkənˈɒmɪkə‍l/",
    "economically": "/ˌiːkənˈɒmɪkli/",
    "economic": "/ˌiːkənˈɒmɪk/",
    "economics": "/ˌiːkənˈɒmɪks/",
    "economies": "/ɪkˈɒnəmɪz/",
    "economised": "/ɪkˈɒnəmˌa‍ɪzd/",
    "economise": "/ɪkˈɒnəmˌa‍ɪz/",
    "economising": "/ɪkˈɒnəmˌa‍ɪzɪŋ/",
    "economist": "/ɪkˈɒnəmˌɪst/",
    "economists": "/ɪkˈɒnəmˌɪsts/",
    "economy": "/ɪkˈɒnəmi/",
    "ecosystem": "/ˈiːkə‍ʊsˌɪstəm/",
    "ecosystems": "/ˈiːkə‍ʊsˌɪstəmz/",
    "ecotourism": "/ˈɛkətˌɔːɹɪzəm/",
    "ecru": "/ˈɛkɹuː/",
    "ecstasies": "/ˈɛkstəsiz/",
    "ecstasy": "/ˈɛkstəsi/",
    "ecstatically": "/ɛkstˈætɪkli/",
    "ecstatic": "/ɛkstˈætɪk/",
    "ectoparasite": "/ˈɛktəpˌæɹɐsˌa‍ɪt/",
    "ectopic": "/ɛktˈɒpɪk/",
    "ectoplasm": "/ˈɛktəplˌæzəm/",
    "ectoplasmic": "/ˌɛktəplˈæzmɪk/",
    "ectothermic": "/ˌɛktəðˈɜːmɪk/",
    "ecu": "/ˈɛkuː/",
    "ecumenical": "/ˌɛkjuːmˈɛnɪkə‍l/",
    "ecumenically": "/ˌɛkjuːmˈɛnɪkli/",
    "eczema": "/ˈɛkzəmɐ/",
    "eczematous": "/ˌɛkzɪmˈætəs/",
    "eddies": "/ˈɛdɪz/",
    "eddy": "/ˈɛdi/",
    "eddying": "/ˈɛdɪɪŋ/",
    "edelweiss": "/ˈɛdɪlwˌe‍ɪs/",
    "edged": "/ˈɛd‍ʒd/",
    "edge": "/ˈɛd‍ʒ/",
    "edger": "/ˈɛd‍ʒɐ/",
    "edges": "/ˈɛd‍ʒɪz/",
    "edgeways": "/ˈɛd‍ʒwe‍ɪz/",
    "edgewise": "/ˈɛd‍ʒwa‍ɪz/",
    "edgier": "/ˈɛd‍ʒɪɐ/",
    "edgiest": "/ˈɛd‍ʒɪəst/",
    "edginess": "/ˈɛd‍ʒɪnəs/",
    "edging": "/ˈɛd‍ʒɪŋ/",
    "edgings": "/ˈɛd‍ʒɪŋz/",
    "edgy": "/ˈɛd‍ʒi/",
    "edh": "/ˈɛd/",
    "edible": "/ˈɛdəbə‍l/",
    "edibles": "/ˈɛdəbə‍lz/",
    "edict": "/ˈiːdɪkt/",
    "edicts": "/ˈiːdɪkts/",
    "edification": "/ˌɛdɪfɪkˈe‍ɪʃən/",
    "edifice": "/ˈɛdɪfɪs/",
    "edifices": "/ˈɛdɪfɪsɪz/",
    "edified": "/ˈɛdɪfˌa‍ɪd/",
    "edify": "/ˈɛdɪfˌa‍ɪ/",
    "edifying": "/ˈɛdɪfˌa‍ɪɪŋ/",
    "edited": "/ˈɛdɪtɪd/",
    "edit": "/ˈɛdɪt/",
    "editing": "/ˈɛdɪtɪŋ/",
    "edition": "/ɪdˈɪʃən/",
    "editions": "/ɪdˈɪʃənz/",
    "editor": "/ˈɛdɪtɐ/",
    "editorial": "/ˌɛdɪtˈɔːɹɪəl/",
    "editorialised": "/ˈɛdɪtˌɔːɹɪəlˌa‍ɪzd/",
    "editorialise": "/ˌɛdɪtˈɔːɹɪəlˌa‍ɪz/",
    "editorialising": "/ˈɛdɪtˌɔːɹɪəlˌa‍ɪzɪŋ/",
    "editorially": "/ˌɛdɪtˈɔːɹɪəli/",
    "editorials": "/ˌɛdɪtˈɔːɹɪəlz/",
    "editors": "/ˈɛdɪtəz/",
    "editorship": "/ˈɛdɪtəʃˌɪp/",
    "edits": "/ˈɛdɪts/",
    "educated": "/ˈɛd‍ʒuːkˌe‍ɪtɪd/",
    "educate": "/ˈɛd‍ʒuːkˌe‍ɪt/",
    "educates": "/ˈɛd‍ʒuːkˌe‍ɪts/",
    "educating": "/ˈɛd‍ʒuːkˌe‍ɪtɪŋ/",
    "educational": "/ˌɛd‍ʒuːkˈe‍ɪʃənə‍l/",
    "educationalist": "/ˌɛd‍ʒuːkˈe‍ɪʃənəlˌɪst/",
    "educationalists": "/ˌɛd‍ʒuːkˈe‍ɪʃənəlˌɪsts/",
    "educationally": "/ˌɛd‍ʒuːkˈe‍ɪʃənə‍li/",
    "education": "/ˌɛd‍ʒuːkˈe‍ɪʃən/",
    "educationist": "/ˌɛd‍ʒuːkˈe‍ɪʃənˌɪst/",
    "educationists": "/ˌɛd‍ʒuːkˈe‍ɪʃənˌɪsts/",
    "educations": "/ˌɛd‍ʒuːkˈe‍ɪʃənz/",
    "educative": "/ˈɛd‍ʒuːkətˌɪv/",
    "educator": "/ˈɛd‍ʒuːkˌe‍ɪtɐ/",
    "educators": "/ˈɛd‍ʒuːkˌe‍ɪtəz/",
    "eduction": "/ɛdˈʌkʃən/",
    "eek": "/ˈiːk/",
    "eel": "/ˈiːl/",
    "eels": "/ˈiːlz/",
    "eelworm": "/ˈiːlwɜːm/",
    "e'en": "/ˈɛən/",
    "e'er": "/ˈe‍ə/",
    "eerie": "/ˈi‍əɹi/",
    "eeriest": "/ˈi‍əɹɪəst/",
    "eerily": "/ˈi‍əɹɪli/",
    "eeriness": "/ˈi‍əɹɪnəs/",
    "eery": "/ˈi‍əɹi/",
    "efface": "/ɪfˈe‍ɪs/",
    "effacement": "/ɪfˈe‍ɪsmənt/",
    "effaces": "/ɪfˈe‍ɪsɪz/",
    "effacing": "/ɪfˈe‍ɪsɪŋ/",
    "effected": "/ɪfˈɛktɪd/",
    "effect": "/ɪfˈɛkt/",
    "effecting": "/ɪfˈɛktɪŋ/",
    "effective": "/ɪfˈɛktɪv/",
    "effectively": "/ɪfˈɛktɪvli/",
    "effectiveness": "/ɪfˈɛktɪvnəs/",
    "effects": "/ɪfˈɛkts/",
    "effectual": "/ɪfˈɛkt‍ʃuːə‍l/",
    "effectually": "/ɪfˈɛkt‍ʃuːə‍li/",
    "effed": "/ˈɛft/",
    "effeminacy": "/ˈɛfɪmˌɪnəsi/",
    "effeminate": "/ɛfˈɛmɪnˌe‍ɪt/",
    "effervesce": "/ˈɛfəvˌɛs/",
    "effervescence": "/ˌɛfəvˈɛsəns/",
    "effervescent": "/ˌɛfəvˈɛsənt/",
    "effete": "/ˈɛfiːt/",
    "efficacious": "/ˌɛfɪkˈe‍ɪʃəs/",
    "efficacy": "/ˈɛfɪkəsi/",
    "efficiencies": "/ɪfˈɪʃənsɪz/",
    "efficiency": "/ɪfˈɪʃənsi/",
    "efficient": "/ɪfˈɪʃənt/",
    "efficiently": "/ɪfˈɪʃəntli/",
    "eff": "/ˌiːˌɛfˈɛf/",
    "effigies": "/ˈɛfɪd‍ʒɪz/",
    "effigy": "/ˈɛfɪd‍ʒi/",
    "effing": "/ˈɛfɪŋ/",
    "efflorescence": "/ˌɛfləɹˈɛsəns/",
    "effluence": "/ˈɛfluːəns/",
    "effluent": "/ˈɛfluːənt/",
    "effluvia": "/ɛflˈuːvi‍ə/",
    "effort": "/ˈɛfət/",
    "effortful": "/ˈɛfətfə‍l/",
    "effortless": "/ˈɛfətləs/",
    "effortlessly": "/ˈɛfətləsli/",
    "effortlessness": "/ˈɛfətləsnəs/",
    "efforts": "/ˈɛfəts/",
    "effrontery": "/ˈɛfɹəntəɹi/",
    "effs": "/ˈɛfs/",
    "effulgent": "/ɪfˈʌld‍ʒənt/",
    "effusion": "/ɪfjˈuːʒən/",
    "effusions": "/ɪfjˈuːʒənz/",
    "effusive": "/ɪfjˈuːsɪv/",
    "effusiveness": "/ɪfjˈuːsɪvnəs/",
    "eft": "/ˈɛft/",
    "egads": "/ˈɛɡædz/",
    "egalitarian": "/ɪɡˌælɪtˈe‍əɹi‍ən/",
    "egalitarianism": "/ɪɡˌælɪtˈe‍əɹi‍ənˌɪzəm/",
    "egestion": "/ˈɛd‍ʒɛst‍ʃən/",
    "eggbeater": "/ˈɛɡbiːtɐ/",
    "eggcup": "/ˈɛɡkʌp/",
    "eggcups": "/ˈɛɡkʌps/",
    "egg": "/ˈɛɡ/",
    "egged": "/ˈɛɡd/",
    "eggers": "/ˈɛɡəz/",
    "egghead": "/ˈɛɡhɛd/",
    "eggheads": "/ˈɛɡhɛdz/",
    "egging": "/ˈɛɡɪŋ/",
    "eggnog": "/ˈɛɡnɒɡ/",
    "eggplant": "/ˈɛɡplænt/",
    "eggplants": "/ˈɛɡplænts/",
    "eggs": "/ˈɛɡz/",
    "eggshell": "/ˈɛɡʃɛl/",
    "eggshells": "/ˈɛɡʃɛlz/",
    "eglantine": "/ˈɛɡlɑːntˌiːn/",
    "egocentric": "/ˌiːɡə‍ʊsˈɛntɹɪk/",
    "ego": "/ˈiːɡə‍ʊ/",
    "egoism": "/ˈiːɡə‍ʊˌɪzəm/",
    "egoist": "/ˈiːɡə‍ʊˌɪst/",
    "egoless": "/ˈiːɡə‍ʊləs/",
    "egomaniacal": "/ˈiːɡə‍ʊmɐnˌa‍ɪ‍əkə‍l/",
    "egomaniac": "/ˌiːɡə‍ʊmˈe‍ɪnɪˌæk/",
    "egos": "/ˈiːɡə‍ʊz/",
    "egotism": "/ˈɛɡətˌɪzəm/",
    "egotist": "/ˈɛɡətˌɪst/",
    "egotistical": "/ˌɛɡətˈɪstɪkə‍l/",
    "egotistic": "/ˌɛɡətˈɪstɪk/",
    "egregious": "/ɪɡɹˈiːd‍ʒəs/",
    "egregiously": "/ɪɡɹˈiːd‍ʒəsli/",
    "egret": "/ˈiːɡɹət/",
    "egrets": "/ˈiːɡɹəts/",
    "eh": "/ˈe‍ɪ/",
    "e": "/ˈiː/",
    "eide": "/ˈa‍ɪd/",
    "eider": "/ˈa‍ɪdɐ/",
    "eiderdown": "/ˈa‍ɪdədˌa‍ʊn/",
    "eiderdowns": "/ˈa‍ɪdədˌa‍ʊnz/",
    "eiders": "/ˈa‍ɪdəz/",
    "eidetic": "/a‍ɪdˈɛtɪk/",
    "eidos": "/ˈa‍ɪdə‍ʊz/",
    "eighteen": "/e‍ɪtˈiːn/",
    "eighteens": "/e‍ɪtˈiːnz/",
    "eighteenth": "/ˈe‍ɪtiːnθ/",
    "eight": "/ˈe‍ɪt/",
    "eightfold": "/ˈe‍ɪtfə‍ʊld/",
    "eighth": "/ˈe‍ɪtθ/",
    "eighths": "/ˈe‍ɪtθs/",
    "eighties": "/ˈe‍ɪtɪz/",
    "eightieth": "/ˈe‍ɪti‍əθ/",
    "eightpence": "/ˈe‍ɪtpəns/",
    "eights": "/ˈe‍ɪts/",
    "eighty": "/ˈe‍ɪti/",
    "einkorn": "/ˈa‍ɪŋkɔːn/",
    "einsteinium": "/a‍ɪnstˈa‍ɪni‍əm/",
    "eisteddfod": "/ˈa‍ɪstɪdfˌɒd/",
    "eisteddfods": "/ˈa‍ɪstɪdfˌɒdz/",
    "either": "/ˈa‍ɪðɐ/",
    "ejaculated": "/ɪd‍ʒˈækjʊlˌe‍ɪtɪd/",
    "ejaculating": "/ɪd‍ʒˈækjʊlˌe‍ɪtɪŋ/",
    "ejaculation": "/ɪd‍ʒˌækjʊlˈe‍ɪʃən/",
    "ejaculations": "/ɪd‍ʒˌækjʊlˈe‍ɪʃənz/",
    "ejaculator": "/ɪd‍ʒˈækjʊlˌe‍ɪtɐ/",
    "ejected": "/ɪd‍ʒˈɛktɪd/",
    "ejecting": "/ɪd‍ʒˈɛktɪŋ/",
    "ejection": "/ɪd‍ʒˈɛkʃən/",
    "ejections": "/ɪd‍ʒˈɛkʃənz/",
    "ejector": "/ɪd‍ʒˈɛktɐ/",
    "ejects": "/ɪd‍ʒˈɛkts/",
    "eked": "/ˈiːkt/",
    "eke": "/ˈiːk/",
    "ekes": "/ˈiːks/",
    "eking": "/ˈiːkɪŋ/",
    "elaborated": "/ɪlˈæbəɹˌe‍ɪtɪd/",
    "elaborately": "/ɪlˈæbəɹˌe‍ɪtli/",
    "elaborateness": "/ɪlˈæbəɹˌe‍ɪtnəs/",
    "elaborates": "/ɪlˈæbəɹˌe‍ɪts/",
    "elaborating": "/ɪlˈæbəɹˌe‍ɪtɪŋ/",
    "elaboration": "/ɪlˌæbəɹˈe‍ɪʃən/",
    "eland": "/ɪlˈænd/",
    "elands": "/ɪlˈændz/",
    "elapids": "/ɪlˈæpɪdz/",
    "elapsed": "/ɪlˈæpsd/",
    "elapse": "/ɪlˈæps/",
    "elapsing": "/ɪlˈæpsɪŋ/",
    "elasticated": "/ɪlˈɑːstɪkˌe‍ɪtɪd/",
    "elasticised": "/ɪlˈɑːstɪsˌa‍ɪzd/",
    "elasticity": "/ɪlɑːstˈɪsɪti/",
    "elastic": "/ɪlˈɑːstɪk/",
    "elated": "/ɪlˈe‍ɪtɪd/",
    "elate": "/ɪlˈe‍ɪt/",
    "elating": "/ɪlˈe‍ɪtɪŋ/",
    "elation": "/ɪlˈe‍ɪʃən/",
    "elbowed": "/ˈɛlbə‍ʊd/",
    "elbow": "/ˈɛlbə‍ʊ/",
    "elbowing": "/ˈɛlbə‍ʊɪŋ/",
    "elbows": "/ˈɛlbə‍ʊz/",
    "eld": "/ˈɛld/",
    "elderberries": "/ˈɛldəbəɹɪz/",
    "elderberry": "/ˈɛldəbəɹi/",
    "elder": "/ˈɛldɐ/",
    "elderflower": "/ˈɛldəflˌa‍ʊɐ/",
    "elderly": "/ˈɛldəli/",
    "elders": "/ˈɛldəz/",
    "eldest": "/ˈɛldəst/",
    "eldritch": "/ˈɛldɹɪt‍ʃ/",
    "elecampane": "/ɪlˈɛkɐmpˌe‍ɪn/",
    "electability": "/ɪlˌɛktəbˈɪlɪti/",
    "electable": "/ɪlˈɛktəbə‍l/",
    "elected": "/ɪlˈɛktɪd/",
    "electing": "/ɪlˈɛktɪŋ/",
    "electioneering": "/ɪlˈɛkʃənˈi‍əɹɪŋ/",
    "electioneer": "/ɪlˈɛkʃənˈi‍ə/",
    "election": "/ɪlˈɛkʃən/",
    "elections": "/ɪlˈɛkʃənz/",
    "elective": "/ɪlˈɛktɪv/",
    "electives": "/ɪlˈɛktɪvz/",
    "elect": "/ɪlˈɛkt/",
    "electoral": "/ɪlˈɛktəɹə‍l/",
    "electorally": "/ɪlˈɛktəɹə‍li/",
    "electorate": "/ɪlˈɛktəɹˌe‍ɪt/",
    "electorates": "/ɪlˈɛktəɹˌe‍ɪts/",
    "elector": "/ɪlˈɛktɐ/",
    "electors": "/ɪlˈɛktəz/",
    "electret": "/ɪlˈɛktɹɪt/",
    "electrical": "/ɪlˈɛktɹɪkə‍l/",
    "electrically": "/ɪlˈɛktɹɪkli/",
    "electrician": "/ɪlɪktɹˈɪʃən/",
    "electricians": "/ɪlɪktɹˈɪʃənz/",
    "electricity": "/ɪlɛktɹˈɪsɪtˌi/",
    "electric": "/ɪlˈɛktɹɪk/",
    "electrics": "/ɪlˈɛktɹɪks/",
    "electrification": "/ɪlˌɛktɹɪfɪkˈe‍ɪʃən/",
    "electrified": "/ɪlˈɛktɹɪfˌa‍ɪd/",
    "electrifies": "/ɪlˈɛktɹɪfˌa‍ɪz/",
    "electrifying": "/ɪlˈɛktɹɪfˌa‍ɪɪŋ/",
    "electrify": "/ɪlˈɛktɹɪfˌa‍ɪ/",
    "electrocardiogram": "/ɪlˌɛktɹə‍ʊkˈɑːdɪˌə‍ʊɡɹæm/",
    "electrocardiograph": "/ɪlˌɛktɹə‍ʊkˈɑːdɪˌə‍ʊɡɹæf/",
    "electrocardiography": "/ɪlˌɛktɹə‍ʊkˌɑːdɪˈə‍ʊɡɹəfi/",
    "electrochemical": "/ɪlˌɛktɹə‍ʊkˈɛmɪkə‍l/",
    "electrocuted": "/ɪlˈɛktɹəkjˌuːtɪd/",
    "electrocute": "/ɪlˈɛktɹəkjˌuːt/",
    "electrocutes": "/ɪlˈɛktɹəkjˌuːts/",
    "electrocuting": "/ɪlˈɛktɹəkjˌuːtɪŋ/",
    "electrocution": "/ɪlˌɛktɹəkjˈuːʃən/",
    "electrocutions": "/ɪlˌɛktɹəkjˈuːʃənz/",
    "electrode": "/ɪlˈɛktɹə‍ʊd/",
    "electrodes": "/ɪlˈɛktɹə‍ʊdz/",
    "electrodynamics": "/ɪlˌɛktɹə‍ʊda‍ɪnˈæmɪks/",
    "electroencephalogram": "/ɪlˌɛktɹə‍ʊənsˈɛfɐlˌɒɡɹæm/",
    "electroencephalograph": "/ɪlˌɛktɹə‍ʊənsˈɛfɐlˌɒɡɹæf/",
    "electroencephalography": "/ɪlˌɛktɹə‍ʊənsˌɛfɐlˈɒɡɹəfi/",
    "electro": "/ɪlˈɛktɹə‍ʊ/",
    "electrolier": "/ɛlˈɛktɹəliɐ/",
    "electroluminescent": "/ɛlˌɛktɹəlˌuːmɪnˈɛsənt/",
    "electrolysis": "/ɛlɪktɹˈɒləsˌɪs/",
    "electrolyte": "/ɛlˈɛktɹəlˌa‍ɪt/",
    "electrolytes": "/ɛlˈɛktɹəlˌa‍ɪts/",
    "electrolytic": "/ɛlˌɛktɹəlˈɪtɪk/",
    "electromagnetic": "/ɪlˌɛktɹə‍ʊmɐɡnˈɛtɪk/",
    "electromagnetism": "/ɪlˌɛktɹə‍ʊmˈæɡnɪtˌɪzəm/",
    "electromagnet": "/ɪlˌɛktɹə‍ʊmˈæɡnɪt/",
    "electromagnets": "/ɪlˌɛktɹə‍ʊmˈæɡnɪts/",
    "electromechanical": "/ɪlˌɛktɹə‍ʊmɪkˈænɪkə‍l/",
    "electromotive": "/ɪlˌɛktɹə‍ʊmˈə‍ʊtɪv/",
    "electronically": "/ˌɛlɪktɹˈɒnɪkli/",
    "electronic": "/ˌɛlɪktɹˈɒnɪk/",
    "electronics": "/ˌɛlɪktɹˈɒnɪks/",
    "electron": "/ɪlˈɛktɹɒn/",
    "electrons": "/ɪlˈɛktɹɒnz/",
    "electroplated": "/ɪlˌɛktɹə‍ʊplˈe‍ɪtɪd/",
    "electroplate": "/ɪlˌɛktɹə‍ʊplˈe‍ɪt/",
    "electroplating": "/ɪlˌɛktɹə‍ʊplˈe‍ɪtɪŋ/",
    "electroshock": "/ɪlˌɛktɹə‍ʊʃˈɒk/",
    "electrostatic": "/ɪlˌɛktɹə‍ʊstˈætɪk/",
    "electrotherapy": "/ɪlˌɛktɹə‍ʊθˈɛɹəpi/",
    "electrotype": "/ɪlˌɛktɹə‍ʊtˈa‍ɪp/",
    "electrum": "/ɪlˈɛktɹəm/",
    "elects": "/ɪlˈɛkts/",
    "elegance": "/ˈɛlɪɡəns/",
    "elegant": "/ˈɛlɪɡənt/",
    "elegantly": "/ˈɛlɪɡəntli/",
    "elegiac": "/ˈɛlɪd‍ʒək/",
    "elegiacs": "/ˈɛlɪd‍ʒəks/",
    "elegies": "/ˈɛlɪd‍ʒɪz/",
    "elegist": "/ˈɛlɪd‍ʒˌɪst/",
    "elegy": "/ˈɛlɪd‍ʒi/",
    "elemental": "/ˌɛlɪmˈɛntə‍l/",
    "elementary": "/ˌɛlɪmˈɛntəɹi/",
    "element": "/ˈɛlɪmənt/",
    "elements": "/ˈɛlɪmənts/",
    "elephant": "/ˈɛlɪfənt/",
    "elephantiasis": "/ˈɛlɪfˌɑːnʃɪˌæsiz/",
    "elephantine": "/ˈɛlɪfˌɑːntiːn/",
    "elephants": "/ˈɛlɪfənts/",
    "elevated": "/ˈɛlɪvˌe‍ɪtɪd/",
    "elevate": "/ˈɛlɪvˌe‍ɪt/",
    "elevates": "/ˈɛlɪvˌe‍ɪts/",
    "elevating": "/ˈɛlɪvˌe‍ɪtɪŋ/",
    "elevation": "/ˌɛlɪvˈe‍ɪʃən/",
    "elevations": "/ˌɛlɪvˈe‍ɪʃənz/",
    "elevator": "/ˈɛlɪvˌe‍ɪtɐ/",
    "elevators": "/ˈɛlɪvˌe‍ɪtəz/",
    "eleven": "/ɪlˈɛvən/",
    "elevenses": "/ɪlˈɛvənsɪz/",
    "elevens": "/ɪlˈɛvənz/",
    "eleventh": "/ɪlˈɛvənθ/",
    "elf": "/ˈɛlf/",
    "elfin": "/ˈɛlfɪn/",
    "elfish": "/ˈɛlfɪʃ/",
    "elfland": "/ˈɛlflənd/",
    "elicited": "/ɪlˈɪsɪtɪd/",
    "eliciting": "/ɪlˈɪsɪtɪŋ/",
    "elicit": "/ɪlˈɪsɪt/",
    "elicits": "/ɪlˈɪsɪts/",
    "elides": "/ɪlˈa‍ɪdz/",
    "eliding": "/ɪlˈa‍ɪdɪŋ/",
    "eligibility": "/ˌɛlɪd‍ʒəbˈɪlɪti/",
    "eligible": "/ˈɛlɪd‍ʒəbə‍l/",
    "eliminated": "/ɪlˈɪmɪnˌe‍ɪtɪd/",
    "eliminate": "/ɪlˈɪmɪnˌe‍ɪt/",
    "eliminates": "/ɪlˈɪmɪnˌe‍ɪts/",
    "eliminating": "/ɪlˈɪmɪnˌe‍ɪtɪŋ/",
    "elimination": "/ɪlˌɪmɪnˈe‍ɪʃən/",
    "eliminations": "/ɪlˌɪmɪnˈe‍ɪʃənz/",
    "eliminator": "/ɪlˈɪmɪnˌe‍ɪtɐ/",
    "eliminators": "/ɪlˈɪmɪnˌe‍ɪtəz/",
    "elision": "/ɪlˈɪʒən/",
    "elite": "/ɪlˈiːt/",
    "elites": "/ɪlˈiːts/",
    "elitism": "/ɪlˈiːtɪzəm/",
    "elitist": "/ɪlˈiːtɪst/",
    "elitists": "/ɪlˈiːtɪsts/",
    "elixir": "/ɪlˈɪksɐ/",
    "elk": "/ˈɛlk/",
    "elks": "/ˈɛlks/",
    "ell": "/ˈɛl/",
    "ellipse": "/ɪlˈɪps/",
    "ellipsis": "/ɪlˈɪpsɪs/",
    "ellipsoid": "/ɪlˈɪpsɔ‍ɪd/",
    "elliptical": "/ɪlˈɪptɪkə‍l/",
    "elliptically": "/ɪlˈɪptɪkli/",
    "elliptic": "/ɪlˈɪptɪk/",
    "ells": "/ˈɛlz/",
    "elm": "/ˈɛlm/",
    "elms": "/ˈɛlmz/",
    "elocution": "/ɪləkjˈuːʃən/",
    "elongated": "/ɪlˈɒŋɡe‍ɪtɪd/",
    "elongate": "/ɪlˈɒŋɡe‍ɪt/",
    "elongates": "/ɪlˈɒŋɡe‍ɪts/",
    "elongating": "/ɪlˈɒŋɡe‍ɪtɪŋ/",
    "elongation": "/ɪləŋɡˈe‍ɪʃən/",
    "eloped": "/ɪlˈə‍ʊpt/",
    "elope": "/ɪlˈə‍ʊp/",
    "elopement": "/ɪlˈə‍ʊpmənt/",
    "elopes": "/ɪlˈə‍ʊps/",
    "eloping": "/ɪlˈə‍ʊpɪŋ/",
    "eloquence": "/ˈɛləkwəns/",
    "eloquent": "/ˈɛləkwənt/",
    "eloquently": "/ˈɛləkwəntli/",
    "else": "/ˈɛls/",
    "els": "/ˈɛlz/",
    "elsewhere": "/ˈɛlswe‍ə/",
    "elucidated": "/ɪlˈuːsɪdˌe‍ɪtɪd/",
    "elucidate": "/ɪlˈuːsɪdˌe‍ɪt/",
    "elucidates": "/ɪlˈuːsɪdˌe‍ɪts/",
    "elucidating": "/ɪlˈuːsɪdˌe‍ɪtɪŋ/",
    "elucidation": "/ɪlˌuːsɪdˈe‍ɪʃən/",
    "eluded": "/ɪlˈuːdɪd/",
    "elude": "/ɪlˈuːd/",
    "eludes": "/ɪlˈuːdz/",
    "eluding": "/ɪlˈuːdɪŋ/",
    "elusive": "/ɪlˈuːsɪv/",
    "elusiveness": "/ɪlˈuːsɪvnəs/",
    "elver": "/ˈɛlvɐ/",
    "elvers": "/ˈɛlvəz/",
    "elves": "/ˈɛlvz/",
    "elvish": "/ˈɛlvɪʃ/",
    "emaciated": "/iːmˈe‍ɪsɪˌe‍ɪtɪd/",
    "emaciation": "/iːmˈe‍ɪsɪˈe‍ɪʃən/",
    "emailed": "/ˈiːme‍ɪld/",
    "emailing": "/ˈiːme‍ɪlɪŋ/",
    "emails": "/ˈiːme‍ɪlz/",
    "emanated": "/ˈɛmɐnˌe‍ɪtɪd/",
    "emanate": "/ˈɛmɐnˌe‍ɪt/",
    "emanates": "/ˈɛmɐnˌe‍ɪts/",
    "emanating": "/ˈɛmɐnˌe‍ɪtɪŋ/",
    "emanation": "/ˌɛmɐnˈe‍ɪʃən/",
    "emanations": "/ˌɛmɐnˈe‍ɪʃənz/",
    "emancipated": "/ɪmˈɑːnsɪpˌe‍ɪtɪd/",
    "emancipate": "/ɪmˈɑːnsɪpˌe‍ɪt/",
    "emancipation": "/ɪmˌɑːnsɪpˈe‍ɪʃən/",
    "emancipator": "/ɪmˈɑːnsɪpˌe‍ɪtɐ/",
    "emasculated": "/ɪmˈæskjʊlˌe‍ɪtɪd/",
    "emasculate": "/ɪmˈæskjʊlˌe‍ɪt/",
    "emasculating": "/ɪmˈæskjʊlˌe‍ɪtɪŋ/",
    "emasculation": "/ɪmˌæskjʊlˈe‍ɪʃən/",
    "embalmed": "/ɛmbˈɑːmd/",
    "embalm": "/ɛmbˈɑːm/",
    "embalmer": "/ɛmbˈɑːmɐ/",
    "embalmers": "/ɛmbˈɑːməz/",
    "embalming": "/ɛmbˈɑːmɪŋ/",
    "embalms": "/ɛmbˈɑːmz/",
    "embankment": "/ɛmbˈæŋkmənt/",
    "embankments": "/ɛmbˈæŋkmənts/",
    "embargoed": "/ɛmbˈɑːɡə‍ʊd/",
    "embargo": "/ɛmbˈɑːɡə‍ʊ/",
    "embargoes": "/ɛmbˈɑːɡə‍ʊz/",
    "embarkation": "/ɛmbɑːkˈe‍ɪʃən/",
    "embarked": "/ɛmbˈɑːkt/",
    "embark": "/ɛmbˈɑːk/",
    "embarking": "/ɛmbˈɑːkɪŋ/",
    "embarks": "/ɛmbˈɑːks/",
    "embarrassed": "/ɛmbˈæɹəst/",
    "embarrass": "/ɛmbˈæɹəs/",
    "embarrasses": "/ɛmbˈæɹəsɪz/",
    "embarrassing": "/ɛmbˈæɹəsɪŋ/",
    "embarrassingly": "/ɛmbˈæɹəsɪŋli/",
    "embarrassment": "/ɛmbˈæɹəsmənt/",
    "embarrassments": "/ɛmbˈæɹəsmənts/",
    "embassies": "/ˈɛmbəsˌɪz/",
    "embassy": "/ˈɛmbəsˌi/",
    "embattled": "/ɛmbˈætə‍ld/",
    "embedded": "/ɛmbˈɛdɪd/",
    "embedding": "/ɛmbˈɛdɪŋ/",
    "embed": "/ɛmbˈɛd/",
    "embeds": "/ɛmbˈɛdz/",
    "embellished": "/ɛmbˈɛlɪʃt/",
    "embellish": "/ɛmbˈɛlɪʃ/",
    "embellishes": "/ɛmbˈɛlɪʃɪz/",
    "embellishing": "/ɛmbˈɛlɪʃɪŋ/",
    "embellishment": "/ɛmbˈɛlɪʃmənt/",
    "embellishments": "/ɛmbˈɛlɪʃmənts/",
    "ember": "/ˈɛmbɐ/",
    "embers": "/ˈɛmbəz/",
    "embezzled": "/ɛmbˈɛzə‍ld/",
    "embezzle": "/ɛmbˈɛzə‍l/",
    "embezzlement": "/ɛmbˈɛzə‍lmənt/",
    "embezzler": "/ɛmbˈɛzlɐ/",
    "embezzling": "/ɛmbˈɛzlɪŋ/",
    "embittered": "/ɛmbˈɪtəd/",
    "embittering": "/ɛmbˈɪtəɹɪŋ/",
    "emblaze": "/ɛmblˈe‍ɪz/",
    "emblazoned": "/ɛmblˈe‍ɪzənd/",
    "emblazon": "/ɛmblˈe‍ɪzən/",
    "emblematic": "/ˌɛmbə‍lmˈætɪk/",
    "emblem": "/ˈɛmbləm/",
    "emblems": "/ˈɛmbləmz/",
    "embodied": "/ɛmbˈɒdɪd/",
    "embodies": "/ɛmbˈɒdɪz/",
    "embodiment": "/ɛmbˈɒdɪmənt/",
    "embodiments": "/ɛmbˈɒdɪmənts/",
    "embody": "/ɛmbˈɒdi/",
    "embodying": "/ɛmbˈɒdɪɪŋ/",
    "emboldened": "/ɛmbˈə‍ʊldənd/",
    "embolden": "/ɛmbˈə‍ʊldən/",
    "emboldens": "/ɛmbˈə‍ʊldənz/",
    "embolectomy": "/ɛmbəlˈɛktəmˌi/",
    "emboli": "/ɛmbˈə‍ʊli/",
    "embolism": "/ˈɛmbə‍ʊlˌɪzəm/",
    "embolus": "/ɛmbˈɒləs/",
    "embonpoint": "/ɛmbˈɒnpɔ‍ɪnt/",
    "embossed": "/ɛmbˈɒst/",
    "emboss": "/ɛmbˈɒs/",
    "embosses": "/ɛmbˈɒsɪz/",
    "embossing": "/ɛmbˈɒsɪŋ/",
    "embouchure": "/ɛmbˈa‍ʊʃjɔː/",
    "embowered": "/ɛmbˈa‍ʊəd/",
    "embraceable": "/ɛmbɹˈe‍ɪsəbə‍l/",
    "embraced": "/ɛmbɹˈe‍ɪst/",
    "embrace": "/ɛmbɹˈe‍ɪs/",
    "embraces": "/ɛmbɹˈe‍ɪsɪz/",
    "embracing": "/ɛmbɹˈe‍ɪsɪŋ/",
    "embrocation": "/ɛmbɹəkˈe‍ɪʃən/",
    "embroidered": "/ɛmbɹˈɔ‍ɪdəd/",
    "embroider": "/ɛmbɹˈɔ‍ɪdɐ/",
    "embroiderer": "/ɛmbɹˈɔ‍ɪdəɹɐ/",
    "embroiderers": "/ɛmbɹˈɔ‍ɪdəɹəz/",
    "embroideries": "/ɛmbɹˈɔ‍ɪdəɹiz/",
    "embroidering": "/ɛmbɹˈɔ‍ɪdəɹɪŋ/",
    "embroiders": "/ɛmbɹˈɔ‍ɪdəz/",
    "embroidery": "/ɛmbɹˈɔ‍ɪdəɹi/",
    "embroiled": "/ɛmbɹˈɔ‍ɪld/",
    "embroil": "/ɛmbɹˈɔ‍ɪl/",
    "embroiling": "/ɛmbɹˈɔ‍ɪlɪŋ/",
    "embroilment": "/ɛmbɹˈɔ‍ɪlmənt/",
    "embroils": "/ɛmbɹˈɔ‍ɪlz/",
    "embryo": "/ˈɛmbɹɪˌə‍ʊ/",
    "embryologist": "/ˌɛmbɹɪˈɒləd‍ʒˌɪst/",
    "embryologists": "/ˌɛmbɹɪˈɒləd‍ʒˌɪsts/",
    "embryology": "/ˌɛmbɹɪˈɒləd‍ʒi/",
    "embryonic": "/ˌɛmbɹɪˈɒnɪk/",
    "embryos": "/ˈɛmbɹɪˌə‍ʊz/",
    "emcee": "/ɛmsˈiː/",
    "emcees": "/ɛmsˈiːz/",
    "em": "/ˈɛm/",
    "emerald": "/ˈɛməɹə‍ld/",
    "emeralds": "/ˈɛməɹə‍ldz/",
    "emerged": "/ɪmˈɜːd‍ʒd/",
    "emerge": "/ɪmˈɜːd‍ʒ/",
    "emergence": "/ɪmˈɜːd‍ʒəns/",
    "emergencies": "/ɪmˈɜːd‍ʒənsiz/",
    "emergency": "/ɪmˈɜːd‍ʒənsi/",
    "emergent": "/ɪmˈɜːd‍ʒənt/",
    "emerges": "/ɪmˈɜːd‍ʒɪz/",
    "emerging": "/ɪmˈɜːd‍ʒɪŋ/",
    "emeritus": "/ɪmˈɛɹɪtəs/",
    "emersed": "/ɪmˈɜːsd/",
    "emersion": "/ɪmˈɜːʃən/",
    "emery": "/ˈɛməɹi/",
    "emetic": "/ɪmˈɛtɪk/",
    "emetics": "/ɪmˈɛtɪks/",
    "emigrant": "/ˈɛmɪɡɹənt/",
    "emigrants": "/ˈɛmɪɡɹənts/",
    "emigrated": "/ˈɛmɪɡɹˌe‍ɪtɪd/",
    "emigrate": "/ˈɛmɪɡɹˌe‍ɪt/",
    "emigrates": "/ˈɛmɪɡɹˌe‍ɪts/",
    "emigrating": "/ˈɛmɪɡɹˌe‍ɪtɪŋ/",
    "emigration": "/ˌɛmɪɡɹˈe‍ɪʃən/",
    "emigrations": "/ˌɛmɪɡɹˈe‍ɪʃənz/",
    "eminence": "/ˈɛmɪnəns/",
    "eminent": "/ˈɛmɪnənt/",
    "eminently": "/ˈɛmɪnəntli/",
    "emirate": "/ˈɛmɪɹˌe‍ɪt/",
    "emirates": "/ˈɛmɪɹˌe‍ɪts/",
    "emir": "/ˈɛmi‍ə/",
    "emirs": "/ˈɛmi‍əz/",
    "emissaries": "/ˈɛmɪsəɹiz/",
    "emissary": "/ˈɛmɪsəɹi/",
    "emission": "/ɪmˈɪʃən/",
    "emissions": "/ɪmˈɪʃənz/",
    "emit": "/ɪmˈɪt/",
    "emits": "/ɪmˈɪts/",
    "emitted": "/ɪmˈɪtɪd/",
    "emitter": "/ɪmˈɪtɐ/",
    "emitters": "/ɪmˈɪtəz/",
    "emitting": "/ɪmˈɪtɪŋ/",
    "emmer": "/ˈɛmɐ/",
    "emmet": "/ˈɛmɪt/",
    "emollient": "/ɪmˈɒli‍ənt/",
    "emoted": "/ɪmˈə‍ʊtɪd/",
    "emote": "/ɪmˈə‍ʊt/",
    "emoticon": "/ɪmˈɒtɪkən/",
    "emoticons": "/ɪmˈɒtɪkənz/",
    "emoting": "/ɪmˈə‍ʊtɪŋ/",
    "emotionalism": "/ɪmˈə‍ʊʃənəlˌɪzəm/",
    "emotionality": "/ɪmˌə‍ʊʃənˈælɪti/",
    "emotionally": "/ɪmˈə‍ʊʃənə‍li/",
    "emotional": "/ɪmˈə‍ʊʃənə‍l/",
    "emotionless": "/ɪmˈə‍ʊʃənləs/",
    "emotion": "/ɪmˈə‍ʊʃən/",
    "emotions": "/ɪmˈə‍ʊʃənz/",
    "emotive": "/ɪmˈə‍ʊtɪv/",
    "empanada": "/ɛmpɐnˈɑːdɐ/",
    "empathetically": "/ˌɛmpɐθˈɛtɪkli/",
    "empathetic": "/ˌɛmpɐθˈɛtɪk/",
    "empathic": "/ɛmpˈæθɪk/",
    "empathised": "/ˈɛmpəθˌa‍ɪzd/",
    "empathise": "/ˈɛmpəθˌa‍ɪz/",
    "empathises": "/ˈɛmpəθˌa‍ɪzɪz/",
    "empathising": "/ˈɛmpəθˌa‍ɪzɪŋ/",
    "empathy": "/ˈɛmpəθi/",
    "emperor": "/ˈɛmpəɹɐ/",
    "emperors": "/ˈɛmpəɹəz/",
    "emphasised": "/ˈɛmfɐsˌa‍ɪzd/",
    "emphasise": "/ˈɛmfɐsˌa‍ɪz/",
    "emphasis": "/ˈɛmfəsˌɪs/",
    "emphasises": "/ˈɛmfɐsˌa‍ɪzɪz/",
    "emphasising": "/ˈɛmfɐsˌa‍ɪzɪŋ/",
    "emphatically": "/ɛmfˈætɪkli/",
    "emphatic": "/ɛmfˈætɪk/",
    "emphysema": "/ɛmfˈa‍ɪsmɐ/",
    "empire": "/ˈɛmpa‍ɪ‍ə/",
    "empires": "/ˈɛmpa‍ɪ‍əz/",
    "empirical": "/ɛmpˈɪɹɪkə‍l/",
    "empirically": "/ɛmpˈɪɹɪkli/",
    "empiricism": "/ɛmpˈɪɹɪsˌɪzəm/",
    "empiricist": "/ɛmpˈɪɹɪsˌɪst/",
    "emplacement": "/ɛmplˈe‍ɪsmənt/",
    "emplacements": "/ɛmplˈe‍ɪsmənts/",
    "employability": "/ɛmplˌɔ‍ɪəbˈɪlɪti/",
    "employable": "/ɛmplˈɔ‍ɪəbə‍l/",
    "employed": "/ɛmplˈɔ‍ɪd/",
    "employee": "/ɛmplˈɔ‍ɪiː/",
    "employees": "/ɛmplˈɔ‍ɪiːz/",
    "employ": "/ɛmplˈɔ‍ɪ/",
    "employer": "/ɛmplˈɔ‍ɪɐ/",
    "employers": "/ɛmplˈɔ‍ɪəz/",
    "employing": "/ɛmplˈɔ‍ɪɪŋ/",
    "employment": "/ɛmplˈɔ‍ɪmənt/",
    "employments": "/ɛmplˈɔ‍ɪmənts/",
    "employs": "/ɛmplˈɔ‍ɪz/",
    "emporia": "/ɛmpˈɔːɹi‍ə/",
    "emporium": "/ɛmpˈɔːɹi‍əm/",
    "emporiums": "/ɛmpˈɔːɹi‍əmz/",
    "empowered": "/ɛmpˈa‍ʊəd/",
    "empower": "/ɛmpˈa‍ʊɐ/",
    "empowering": "/ɛmpˈa‍ʊəɹɪŋ/",
    "empowerment": "/ɛmpˈa‍ʊəmənt/",
    "empowers": "/ɛmpˈa‍ʊəz/",
    "empress": "/ˈɛmpɹɛs/",
    "empresses": "/ˈɛmpɹɛsɪz/",
    "emptied": "/ˈɛmptɪd/",
    "emptier": "/ˈɛmptɪɐ/",
    "empties": "/ˈɛmptɪz/",
    "emptiest": "/ˈɛmptɪəst/",
    "emptiness": "/ˈɛmptɪnəs/",
    "emptor": "/ɛmptˈɔː/",
    "empty": "/ˈɛmpti/",
    "emptying": "/ˈɛmptɪɪŋ/",
    "empurpled": "/ɛmpˈɜːpə‍ld/",
    "empyema": "/ɛmpɪˈɛmɐ/",
    "ems": "/ˈɛmz/",
    "emu": "/ˈiːmjuː/",
    "emulated": "/ˈɛmjʊlˌe‍ɪtɪd/",
    "emulate": "/ˈɛmjʊlˌe‍ɪt/",
    "emulates": "/ˈɛmjʊlˌe‍ɪts/",
    "emulating": "/ˈɛmjʊlˌe‍ɪtɪŋ/",
    "emulation": "/ˌɛmjʊlˈe‍ɪʃən/",
    "emulator": "/ˈɛmjʊlˌe‍ɪtɐ/",
    "emulous": "/ˈɛmjʊləs/",
    "emulsification": "/ɪmˌʌlsɪfɪkˈe‍ɪʃən/",
    "emulsified": "/ɪmˈʌlsɪfˌa‍ɪd/",
    "emulsifier": "/ɪmˈʌlsɪfˌa‍ɪ‍ə/",
    "emulsifiers": "/ɪmˈʌlsɪfˌa‍ɪ‍əz/",
    "emulsifies": "/ɪmˈʌlsɪfˌa‍ɪz/",
    "emulsifying": "/ɪmˈʌlsɪfˌa‍ɪɪŋ/",
    "emulsify": "/ɪmˈʌlsɪfˌa‍ɪ/",
    "emulsion": "/ɪmˈʌlʃən/",
    "emulsions": "/ɪmˈʌlʃənz/",
    "emus": "/ˈiːmjuːz/",
    "enabled": "/ɛnˈe‍ɪbə‍ld/",
    "enable": "/ɛnˈe‍ɪbə‍l/",
    "enabler": "/ɛnˈe‍ɪblɐ/",
    "enablers": "/ɛnˈe‍ɪbləz/",
    "enables": "/ɛnˈe‍ɪbə‍lz/",
    "enabling": "/ɛnˈe‍ɪblɪŋ/",
    "enacted": "/ɛnˈæktɪd/",
    "enact": "/ɛnˈækt/",
    "enacting": "/ɛnˈæktɪŋ/",
    "enactment": "/ɛnˈæktmənt/",
    "enactments": "/ɛnˈæktmənts/",
    "enactor": "/ɛnˈæktɐ/",
    "enacts": "/ɛnˈækts/",
    "enamelled": "/ɪnˈæmə‍ld/",
    "enamelling": "/ɪnˈæməlɪŋ/",
    "enamel": "/ɪnˈæmə‍l/",
    "enamels": "/ɪnˈæmə‍lz/",
    "enamoured": "/ɪnˈæməd/",
    "enate": "/ɛnˈe‍ɪt/",
    "encamped": "/ɛnkˈæmpt/",
    "encamp": "/ɛnkˈæmp/",
    "encampment": "/ɛnkˈæmpmənt/",
    "encampments": "/ɛnkˈæmpmənts/",
    "encapsulated": "/ɛnkˈæpsjʊlˌe‍ɪtɪd/",
    "encapsulate": "/ɛnkˈæpsjʊlˌe‍ɪt/",
    "encapsulates": "/ɛnkˈæpsjʊlˌe‍ɪts/",
    "encapsulating": "/ɛnkˈæpsjʊlˌe‍ɪtɪŋ/",
    "encapsulation": "/ɛnkˌæpsuːlˈe‍ɪʃən/",
    "encased": "/ɛnkˈe‍ɪst/",
    "encase": "/ɛnkˈe‍ɪs/",
    "encases": "/ɛnkˈe‍ɪsɪz/",
    "encasing": "/ɛnkˈe‍ɪsɪŋ/",
    "encaustic": "/ɛnkˈɔːstɪk/",
    "encephalitis": "/ɛnsˌɛfɐlˈa‍ɪtɪs/",
    "encephalopathy": "/ɛnsˌɛfɐlˈɒpəθi/",
    "enchained": "/ɛnt‍ʃˈe‍ɪnd/",
    "enchanted": "/ɛnt‍ʃˈɑːntɪd/",
    "enchant": "/ɛnt‍ʃˈɑːnt/",
    "enchanter": "/ɛnt‍ʃˈɑːntɐ/",
    "enchanters": "/ɛnt‍ʃˈɑːntəz/",
    "enchanting": "/ɛnt‍ʃˈɑːntɪŋ/",
    "enchantment": "/ɛnt‍ʃˈɑːntmənt/",
    "enchantments": "/ɛnt‍ʃˈɑːntmənts/",
    "enchantress": "/ɛnt‍ʃˈɑːntɹəs/",
    "enchants": "/ɛnt‍ʃˈɑːnts/",
    "enchilada": "/ɛnt‍ʃɪlˈɑːdɐ/",
    "enchiladas": "/ɛnt‍ʃɪlˈɑːdəz/",
    "enciphered": "/ɛnsˈa‍ɪfəd/",
    "encircled": "/ɛnsˈɜːkə‍ld/",
    "encircle": "/ɛnsˈɜːkə‍l/",
    "encirclement": "/ɛnsˈɜːkə‍lmənt/",
    "encircles": "/ɛnsˈɜːkə‍lz/",
    "encircling": "/ɛnsˈɜːklɪŋ/",
    "enclave": "/ˈɛnkle‍ɪv/",
    "enclaves": "/ˈɛnkle‍ɪvz/",
    "enclosed": "/ɛnklˈə‍ʊzd/",
    "enclose": "/ɛnklˈə‍ʊz/",
    "encloses": "/ɛnklˈə‍ʊzɪz/",
    "enclosing": "/ɛnklˈə‍ʊzɪŋ/",
    "enclosure": "/ɛnklˈə‍ʊʒɐ/",
    "enclosures": "/ɛnklˈə‍ʊʒəz/",
    "encoded": "/ɛnkˈə‍ʊdɪd/",
    "encode": "/ɛnkˈə‍ʊd/",
    "encoder": "/ɛnkˈə‍ʊdɐ/",
    "encodes": "/ɛnkˈə‍ʊdz/",
    "encoding": "/ɛnkˈə‍ʊdɪŋ/",
    "encomium": "/ɛnkˈə‍ʊmi‍əm/",
    "encompassed": "/ɛnkˈʌmpəst/",
    "encompass": "/ɛnkˈʌmpəs/",
    "encompasses": "/ɛnkˈʌmpəsɪz/",
    "encompassing": "/ɛnkˈʌmpəsɪŋ/",
    "encored": "/ˈɒnkəd/",
    "encore": "/ˈɒnkɔː/",
    "encores": "/ˈɒnkɔːz/",
    "encountered": "/ɛnkˈa‍ʊntəd/",
    "encounter": "/ɛnkˈa‍ʊntɐ/",
    "encountering": "/ɛnkˈa‍ʊntəɹɪŋ/",
    "encounters": "/ɛnkˈa‍ʊntəz/",
    "encouraged": "/ɛnkˈʌɹɪd‍ʒd/",
    "encourage": "/ɛnkˈʌɹɪd‍ʒ/",
    "encouragement": "/ɛnkˈʌɹɪd‍ʒmənt/",
    "encourager": "/ɛnkˈʌɹɪd‍ʒɐ/",
    "encourages": "/ɛnkˈʌɹɪd‍ʒɪz/",
    "encouraging": "/ɛnkˈʌɹɪd‍ʒɪŋ/",
    "encouragingly": "/ɛnkˈʌɹɪd‍ʒɪŋli/",
    "encroached": "/ɛnkɹˈə‍ʊt‍ʃt/",
    "encroach": "/ɛnkɹˈə‍ʊt‍ʃ/",
    "encroaches": "/ɛnkɹˈə‍ʊt‍ʃɪz/",
    "encroaching": "/ɛnkɹˈə‍ʊt‍ʃɪŋ/",
    "encroachment": "/ɛnkɹˈə‍ʊt‍ʃmənt/",
    "encroachments": "/ɛnkɹˈə‍ʊt‍ʃmənts/",
    "encrustation": "/ɛnkɹəstˈe‍ɪʃən/",
    "encrustations": "/ɛnkɹəstˈe‍ɪʃənz/",
    "encrusted": "/ɛnkɹˈʌstɪd/",
    "encrust": "/ɛnkɹˈʌst/",
    "encrusting": "/ɛnkɹˈʌstɪŋ/",
    "encrusts": "/ɛnkɹˈʌsts/",
    "encrypted": "/ɛnkɹˈɪptɪd/",
    "encrypt": "/ɛnkɹˈɪpt/",
    "encrypting": "/ɛnkɹˈɪptɪŋ/",
    "encryption": "/ɛnkɹˈɪpʃən/",
    "encryptions": "/ɛnkɹˈɪpʃənz/",
    "encrypts": "/ɛnkɹˈɪpts/",
    "encumbered": "/ɛnkˈʌmbəd/",
    "encumber": "/ɛnkˈʌmbɐ/",
    "encumbrance": "/ɛnkˈʌmbɹəns/",
    "encumbrances": "/ɛnkˈʌmbɹənsɪz/",
    "encyclical": "/ɛnsˈɪklɪkə‍l/",
    "encyclopaedia": "/ɛnsˌa‍ɪkləpˈiːdi‍ə/",
    "encyclopaedias": "/ɛnsˌa‍ɪkləpˈiːdi‍əz/",
    "encyclopedia": "/ɛnsˌa‍ɪklə‍ʊpˈiːdi‍ə/",
    "encyclopedias": "/ɛnsˌa‍ɪklə‍ʊpˈiːdi‍əz/",
    "encyclopedic": "/ɛnsˌa‍ɪklə‍ʊpˈiːdɪk/",
    "endangered": "/ɛndˈe‍ɪnd‍ʒəd/",
    "endanger": "/ɛndˈe‍ɪnd‍ʒɐ/",
    "endangering": "/ɛndˈe‍ɪnd‍ʒəɹɪŋ/",
    "endangerment": "/ɛndˈe‍ɪnd‍ʒəmənt/",
    "endangers": "/ɛndˈe‍ɪnd‍ʒəz/",
    "endeared": "/ɛndˈi‍əd/",
    "endear": "/ɛndˈi‍ə/",
    "endearing": "/ɛndˈi‍əɹɪŋ/",
    "endearingly": "/ɛndˈi‍əɹɪŋli/",
    "endearment": "/ɛndˈi‍əmənt/",
    "endearments": "/ɛndˈi‍əmənts/",
    "endears": "/ɛndˈi‍əz/",
    "endeavoured": "/ɛndˈɛvəd/",
    "endeavour": "/ɛndˈɛvɐ/",
    "endeavouring": "/ɛndˈɛvɜːɹɪŋ/",
    "endeavours": "/ɛndˈɛvəz/",
    "ended": "/ˈɛndɪd/",
    "endemic": "/ɛndˈɛmɪk/",
    "end": "/ˈɛnd/",
    "endgame": "/ˈɛndɡe‍ɪm/",
    "endgames": "/ˈɛndɡe‍ɪmz/",
    "ending": "/ˈɛndɪŋ/",
    "endings": "/ˈɛndɪŋz/",
    "endive": "/ˈɛndɪv/",
    "endives": "/ˈɛndɪvz/",
    "endless": "/ˈɛndləs/",
    "endlessly": "/ˈɛndləsli/",
    "endlessness": "/ˈɛndləsnəs/",
    "endocardial": "/ˌɛndə‍ʊkˈɑːdɪəl/",
    "endocarditis": "/ˌɛndə‍ʊkɑːdˈa‍ɪtɪs/",
    "endocarp": "/ˈɛndə‍ʊkˌɑːp/",
    "endocrine": "/ˈɛndə‍ʊkɹˌa‍ɪn/",
    "endocrinologist": "/ˌɛndə‍ʊkɹɪnˈɒləd‍ʒˌɪst/",
    "endocrinology": "/ˌɛndə‍ʊkɹɪnˈɒləd‍ʒi/",
    "endogamy": "/ˈɛndə‍ʊɡˌæmi/",
    "endogenous": "/ɛndˈə‍ʊd‍ʒənəs/",
    "endometriosis": "/ˌɛndə‍ʊmˌɛtɹɪˈə‍ʊsɪs/",
    "endometrium": "/ˌɛndə‍ʊmˈɛtɹi‍əm/",
    "endorphin": "/ɛndˈɔːfɪn/",
    "endorphins": "/ɛndˈɔːfɪnz/",
    "endorsable": "/ɛndˈɔːsəbə‍l/",
    "endorsed": "/ɛndˈɔːsd/",
    "endorse": "/ɛndˈɔːs/",
    "endorsement": "/ɛndˈɔːsmənt/",
    "endorsements": "/ɛndˈɔːsmənts/",
    "endorser": "/ɛndˈɔːsɐ/",
    "endorses": "/ɛndˈɔːsɪz/",
    "endorsing": "/ɛndˈɔːsɪŋ/",
    "endoscope": "/ˈɛndə‍ʊskˌə‍ʊp/",
    "endoscopes": "/ˈɛndə‍ʊskˌə‍ʊps/",
    "endoscopic": "/ˌɛndə‍ʊskˈɒpɪk/",
    "endoscopy": "/ɛndˈə‍ʊskəpi/",
    "endoskeleton": "/ˈɛndə‍ʊskˌɛlɪtən/",
    "endothermic": "/ˌɛndə‍ʊθˈɜːmɪk/",
    "endowed": "/ɛndˈa‍ʊd/",
    "endow": "/ɛndˈa‍ʊ/",
    "endowing": "/ɛndˈa‍ʊɪŋ/",
    "endowment": "/ɛndˈa‍ʊmənt/",
    "endowments": "/ɛndˈa‍ʊmənts/",
    "endows": "/ɛndˈa‍ʊz/",
    "endpoint": "/ˈɛndpɔ‍ɪnt/",
    "ends": "/ˈɛndz/",
    "endue": "/ɛndjˈuː/",
    "endurable": "/ɛndjˈɔːɹəbə‍l/",
    "endurance": "/ɛndjˈɔːɹəns/",
    "endured": "/ɛndjˈɔːd/",
    "endure": "/ɛndjˈɔː/",
    "endures": "/ɛndjˈɔːz/",
    "enduring": "/ɛndjˈɔːɹɪŋ/",
    "enema": "/ˈɛnəmɐ/",
    "enemas": "/ˈɛnəməz/",
    "enemies": "/ˈɛnəmɪz/",
    "enemy": "/ˈɛnəmi/",
    "en": "/ˈɛn/",
    "energetically": "/ˌɛnəd‍ʒˈɛtɪkli/",
    "energetic": "/ˌɛnəd‍ʒˈɛtɪk/",
    "energies": "/ˈɛnəd‍ʒɪz/",
    "energised": "/ˈɛnəd‍ʒˌa‍ɪzd/",
    "energise": "/ˈɛnəd‍ʒˌa‍ɪz/",
    "energiser": "/ˈɛnəd‍ʒˌa‍ɪzɐ/",
    "energises": "/ˈɛnəd‍ʒˌa‍ɪzɪz/",
    "energising": "/ˈɛnəd‍ʒˌa‍ɪzɪŋ/",
    "energy": "/ˈɛnəd‍ʒi/",
    "enervated": "/ˈɛnəvˌe‍ɪtɪd/",
    "enervate": "/ˈɛnəvˌe‍ɪt/",
    "enervating": "/ˈɛnəvˌe‍ɪtɪŋ/",
    "enervation": "/ˌɛnəvˈe‍ɪʃən/",
    "enfeebled": "/ɛnfˈiːbə‍ld/",
    "enfilade": "/ɛnfˈɪle‍ɪd/",
    "enfleurage": "/ɛnflˈɜːɹɪd‍ʒ/",
    "enfolded": "/ɛnfˈə‍ʊldɪd/",
    "enfold": "/ɛnfˈə‍ʊld/",
    "enfolding": "/ɛnfˈə‍ʊldɪŋ/",
    "enfolds": "/ɛnfˈə‍ʊldz/",
    "enforceability": "/ɛnfˌɔːsəbˈɪlɪti/",
    "enforceable": "/ɛnfˈɔːsəbə‍l/",
    "enforced": "/ɛnfˈɔːst/",
    "enforce": "/ɛnfˈɔːs/",
    "enforcement": "/ɛnfˈɔːsmənt/",
    "enforcements": "/ɛnfˈɔːsmənts/",
    "enforcer": "/ɛnfˈɔːsɐ/",
    "enforcers": "/ɛnfˈɔːsəz/",
    "enforces": "/ɛnfˈɔːsɪz/",
    "enforcing": "/ɛnfˈɔːsɪŋ/",
    "enfranchised": "/ɛnfɹˈɑːnt‍ʃa‍ɪzd/",
    "enfranchise": "/ɛnfɹˈɑːnt‍ʃa‍ɪz/",
    "enfranchisement": "/ɛnfɹˈɑːnt‍ʃa‍ɪzmənt/",
    "engaged": "/ɛnɡˈe‍ɪd‍ʒd/",
    "engage": "/ɛnɡˈe‍ɪd‍ʒ/",
    "engagement": "/ɛnɡˈe‍ɪd‍ʒmənt/",
    "engagements": "/ɛnɡˈe‍ɪd‍ʒmənts/",
    "engages": "/ɛnɡˈe‍ɪd‍ʒɪz/",
    "engaging": "/ɛnɡˈe‍ɪd‍ʒɪŋ/",
    "engendered": "/ɛnd‍ʒˈɛndəd/",
    "engender": "/ɛnd‍ʒˈɛndɐ/",
    "engendering": "/ɛnd‍ʒˈɛndəɹɪŋ/",
    "engenders": "/ɛnd‍ʒˈɛndəz/",
    "engined": "/ˈɛnd‍ʒɪnd/",
    "engine": "/ˈɛnd‍ʒɪn/",
    "engineered": "/ˌɛnd‍ʒɪnˈi‍əd/",
    "engineer": "/ˌɛnd‍ʒɪnˈi‍ə/",
    "engineering": "/ˌɛnd‍ʒɪnˈi‍əɹɪŋ/",
    "engineers": "/ˌɛnd‍ʒɪnˈi‍əz/",
    "engines": "/ˈɛnd‍ʒɪnz/",
    "english": "/ˈɪŋɡlɪʃ/",
    "engorged": "/ɛnɡˈɔːd‍ʒd/",
    "engrained": "/ɛnɡɹˈe‍ɪnd/",
    "engrain": "/ɛnɡɹˈe‍ɪn/",
    "engraved": "/ɛnɡɹˈe‍ɪvd/",
    "engrave": "/ɛnɡɹˈe‍ɪv/",
    "engraver": "/ɛnɡɹˈe‍ɪvɐ/",
    "engravers": "/ɛnɡɹˈe‍ɪvəz/",
    "engraves": "/ɛnɡɹˈe‍ɪvz/",
    "engraving": "/ɛnɡɹˈe‍ɪvɪŋ/",
    "engravings": "/ɛnɡɹˈe‍ɪvɪŋz/",
    "engrossed": "/ɛnɡɹˈə‍ʊst/",
    "engross": "/ɛnɡɹˈə‍ʊs/",
    "engrossing": "/ɛnɡɹˈə‍ʊsɪŋ/",
    "engulfed": "/ɛnɡˈʌlft/",
    "engulf": "/ɛnɡˈʌlf/",
    "engulfing": "/ɛnɡˈʌlfɪŋ/",
    "engulfs": "/ɛnɡˈʌlfs/",
    "enhanced": "/ɛnhˈɑːnst/",
    "enhance": "/ɛnhˈɑːns/",
    "enhancement": "/ɛnhˈɑːnsmənt/",
    "enhancements": "/ɛnhˈɑːnsmənts/",
    "enhancer": "/ɛnhˈɑːnsɐ/",
    "enhancers": "/ɛnhˈɑːnsəz/",
    "enhances": "/ɛnhˈɑːnsɪz/",
    "enhancing": "/ɛnhˈɑːnsɪŋ/",
    "enigma": "/ɛnˈɪɡmɐ/",
    "enigmas": "/ɛnˈɪɡməz/",
    "enigmatically": "/ˌɛnɪɡmˈætɪkli/",
    "enigmatic": "/ˌɛnɪɡmˈætɪk/",
    "enjoined": "/ɛnd‍ʒˈɔ‍ɪnd/",
    "enjoin": "/ɛnd‍ʒˈɔ‍ɪn/",
    "enjoining": "/ɛnd‍ʒˈɔ‍ɪnɪŋ/",
    "enjoyable": "/ɛnd‍ʒˈɔ‍ɪəbə‍l/",
    "enjoyably": "/ɛnd‍ʒˈɔ‍ɪəbli/",
    "enjoyed": "/ɛnd‍ʒˈɔ‍ɪd/",
    "enjoy": "/ɛnd‍ʒˈɔ‍ɪ/",
    "enjoying": "/ɛnd‍ʒˈɔ‍ɪɪŋ/",
    "enjoyment": "/ɛnd‍ʒˈɔ‍ɪmənt/",
    "enjoyments": "/ɛnd‍ʒˈɔ‍ɪmənts/",
    "enjoys": "/ɛnd‍ʒˈɔ‍ɪz/",
    "enlarged": "/ɛnlˈɑːd‍ʒd/",
    "enlarge": "/ɛnlˈɑːd‍ʒ/",
    "enlargement": "/ɛnlˈɑːd‍ʒmənt/",
    "enlargements": "/ɛnlˈɑːd‍ʒmənts/",
    "enlarger": "/ɛnlˈɑːd‍ʒɐ/",
    "enlarges": "/ɛnlˈɑːd‍ʒɪz/",
    "enlarging": "/ɛnlˈɑːd‍ʒɪŋ/",
    "enlightened": "/ɛnlˈa‍ɪtənd/",
    "enlighten": "/ɛnlˈa‍ɪtən/",
    "enlightening": "/ɛnlˈa‍ɪtənɪŋ/",
    "enlightenment": "/ɛnlˈa‍ɪtənmənt/",
    "enlightens": "/ɛnlˈa‍ɪtənz/",
    "enlisted": "/ɛnlˈɪstɪd/",
    "enlist": "/ɛnlˈɪst/",
    "enlisting": "/ɛnlˈɪstɪŋ/",
    "enlistment": "/ɛnlˈɪstmənt/",
    "enlists": "/ɛnlˈɪsts/",
    "enlivened": "/ɛnlˈa‍ɪvənd/",
    "enliven": "/ɛnlˈa‍ɪvən/",
    "enlivening": "/ɛnlˈa‍ɪvənɪŋ/",
    "enlivens": "/ɛnlˈa‍ɪvənz/",
    "enmeshed": "/ɛnmˈɛʃt/",
    "enmities": "/ˈɛnmɪtiz/",
    "enmity": "/ˈɛnmɪti/",
    "ennobled": "/ɛnˈə‍ʊbə‍ld/",
    "ennobling": "/ɛnˈə‍ʊblɪŋ/",
    "ennui": "/ɛnjˈuːi/",
    "enormities": "/ɪnˈɔːmɪtiz/",
    "enormity": "/ɪnˈɔːmɪti/",
    "enormously": "/ɪnˈɔːməsli/",
    "enormous": "/ɪnˈɔːməs/",
    "enough": "/ɪnˈʌf/",
    "enquired": "/ɛnkwˈa‍ɪ‍əd/",
    "enquire": "/ɛnkwˈa‍ɪ‍ə/",
    "enquirer": "/ɛnkwˈa‍ɪ‍əɹɐ/",
    "enquirers": "/ɛnkwˈa‍ɪ‍əɹəz/",
    "enquires": "/ɛnkwˈa‍ɪ‍əz/",
    "enquiries": "/ɛnkwˈa‍ɪ‍əɹɪz/",
    "enquiring": "/ɛnkwˈa‍ɪ‍əɹɪŋ/",
    "enquiry": "/ɛnkwˈa‍ɪ‍əɹi/",
    "enraged": "/ɛnɹˈe‍ɪd‍ʒd/",
    "enrage": "/ɛnɹˈe‍ɪd‍ʒ/",
    "enrages": "/ɛnɹˈe‍ɪd‍ʒz/",
    "enraging": "/ɛnɹˈe‍ɪd‍ʒɪŋ/",
    "enraptured": "/ɛnɹˈæpt‍ʃəd/",
    "enriched": "/ɛnɹˈɪt‍ʃt/",
    "enrich": "/ɛnɹˈɪt‍ʃ/",
    "enriches": "/ɛnɹˈɪt‍ʃɪz/",
    "enriching": "/ɛnɹˈɪt‍ʃɪŋ/",
    "enrichment": "/ɛnɹˈɪt‍ʃmənt/",
    "enrobed": "/ɛnɹˈə‍ʊbd/",
    "enrol": "/ɛnɹˈə‍ʊl/",
    "enrolled": "/ɛnɹˈə‍ʊld/",
    "enroll": "/ɛnɹˈə‍ʊl/",
    "enrolling": "/ɛnɹˈə‍ʊlɪŋ/",
    "enrollment": "/ɛnɹˈə‍ʊlmənt/",
    "enrolment": "/ɛnɹˈə‍ʊlmənt/",
    "enrolments": "/ɛnɹˈə‍ʊlmənts/",
    "enrols": "/ɛnɹˈə‍ʊlz/",
    "ensconced": "/ɛnskˈɒnst/",
    "ensemble": "/ɒnsˈɒmbə‍l/",
    "ensembles": "/ɒnsˈɒmbə‍lz/",
    "ens": "/ˈɛnz/",
    "enshrined": "/ɛnʃɹˈa‍ɪnd/",
    "enshrine": "/ɛnʃɹˈa‍ɪn/",
    "enshrines": "/ɛnʃɹˈa‍ɪnz/",
    "enshrining": "/ɛnʃɹˈa‍ɪnɪŋ/",
    "enshrouded": "/ɛnʃɹˈa‍ʊdɪd/",
    "ensign": "/ˈɛnsa‍ɪn/",
    "ensigns": "/ˈɛnsa‍ɪnz/",
    "enslaved": "/ɛnslˈe‍ɪvd/",
    "enslave": "/ɛnslˈe‍ɪv/",
    "enslavement": "/ɛnslˈe‍ɪvmənt/",
    "enslaver": "/ɛnslˈe‍ɪvɐ/",
    "enslaves": "/ɛnslˈe‍ɪvz/",
    "enslaving": "/ɛnslˈe‍ɪvɪŋ/",
    "ensnared": "/ɛnsnˈe‍əd/",
    "ensnare": "/ɛnsnˈe‍ə/",
    "ensnares": "/ɛnsnˈe‍əz/",
    "ensnaring": "/ɛnsnˈe‍əɹɪŋ/",
    "ensued": "/ɛnsjˈuːd/",
    "ensue": "/ɛnsjˈuː/",
    "ensues": "/ɛnsjˈuːz/",
    "ensuing": "/ɛnsjˈuːɪŋ/",
    "ensured": "/ɛnʃˈɔːd/",
    "ensure": "/ɛnʃˈɔː/",
    "ensures": "/ɛnʃˈɔːz/",
    "ensuring": "/ɛnʃˈɔːɹɪŋ/",
    "entablature": "/ɛntˈæblət‍ʃɐ/",
    "entailed": "/ɛntˈe‍ɪld/",
    "entail": "/ɛntˈe‍ɪl/",
    "entails": "/ɛntˈe‍ɪlz/",
    "entangled": "/ɛntˈæŋɡə‍ld/",
    "entangle": "/ɛntˈæŋɡə‍l/",
    "entanglement": "/ɛntˈæŋɡə‍lmənt/",
    "entanglements": "/ɛntˈæŋɡə‍lmənts/",
    "entangles": "/ɛntˈæŋɡə‍lz/",
    "entangling": "/ɛntˈæŋɡəlɪŋ/",
    "entasis": "/ɛntˈæsiz/",
    "entente": "/ɒntˈɒnt/",
    "entered": "/ˈɛntəd/",
    "enter": "/ˈɛntɐ/",
    "entering": "/ˈɛntəɹɪŋ/",
    "enteritis": "/ˌɛntəɹˈa‍ɪtɪs/",
    "enterotomy": "/ˌɛntəɹˈə‍ʊtəmi/",
    "enterprise": "/ˈɛntəpɹˌa‍ɪz/",
    "enterprises": "/ˈɛntəpɹˌa‍ɪzɪz/",
    "enterprising": "/ˈɛntəpɹˌa‍ɪzɪŋ/",
    "enters": "/ˈɛntəz/",
    "entertained": "/ˌɛntətˈe‍ɪnd/",
    "entertain": "/ˌɛntətˈe‍ɪn/",
    "entertainer": "/ˌɛntətˈe‍ɪnɐ/",
    "entertainers": "/ˌɛntətˈe‍ɪnəz/",
    "entertaining": "/ˌɛntətˈe‍ɪnɪŋ/",
    "entertainingly": "/ˌɛntətˈe‍ɪnɪŋli/",
    "entertainment": "/ˌɛntətˈe‍ɪnmənt/",
    "entertainments": "/ˌɛntətˈe‍ɪnmənts/",
    "entertains": "/ˌɛntətˈe‍ɪnz/",
    "enthral": "/ɛnθɹˈɔːl/",
    "enthralled": "/ɛnθɹˈɔːld/",
    "enthralling": "/ɛnθɹˈɔːlɪŋ/",
    "enthrals": "/ɛnθɹˈɔːlz/",
    "enthroned": "/ɛnθɹˈə‍ʊnd/",
    "enthronement": "/ɛnθɹˈə‍ʊnmənt/",
    "enthused": "/ɛnθjˈuːsd/",
    "enthuse": "/ɛnθjˈuːs/",
    "enthuses": "/ɛnθjˈuːsɪz/",
    "enthusiasm": "/ɛnθjˈuːzɪˌæzəm/",
    "enthusiasms": "/ɛnθjˈuːzɪˌæzəmz/",
    "enthusiast": "/ɛnθjˈuːzɪˌæst/",
    "enthusiastically": "/ɛnθjˌuːzɪˈæstɪkli/",
    "enthusiastic": "/ɛnθjˌuːzɪˈæstɪk/",
    "enthusiasts": "/ɛnθjˈuːzɪˌæsts/",
    "enthusing": "/ɛnθjˈuːsɪŋ/",
    "enticed": "/ɛntˈa‍ɪst/",
    "entice": "/ɛntˈa‍ɪs/",
    "enticement": "/ɛntˈa‍ɪsmənt/",
    "enticements": "/ɛntˈa‍ɪsmənts/",
    "entices": "/ɛntˈa‍ɪsɪz/",
    "enticing": "/ɛntˈa‍ɪsɪŋ/",
    "enticingly": "/ɛntˈa‍ɪsɪŋli/",
    "entire": "/ɛntˈa‍ɪ‍ə/",
    "entirely": "/ɛntˈa‍ɪ‍əli/",
    "entirety": "/ɛntˈa‍ɪɹɪti/",
    "entities": "/ˈɛntɪtiz/",
    "entitled": "/ɛntˈa‍ɪtə‍ld/",
    "entitle": "/ɛntˈa‍ɪtə‍l/",
    "entitlement": "/ɛntˈa‍ɪtə‍lmənt/",
    "entitlements": "/ɛntˈa‍ɪtə‍lmənts/",
    "entitles": "/ɛntˈa‍ɪtə‍lz/",
    "entitling": "/ɛntˈa‍ɪtlɪŋ/",
    "entity": "/ˈɛntɪti/",
    "entombed": "/ɛntˈuːmd/",
    "entomb": "/ɛntˈuːm/",
    "entombing": "/ɛntˈuːmɪŋ/",
    "entombment": "/ɛntˈuːmmənt/",
    "entombs": "/ɛntˈuːmz/",
    "entomological": "/ɛntˌɒməlˈɒd‍ʒɪkə‍l/",
    "entomologist": "/ɛntəmˈɒləd‍ʒˌɪst/",
    "entomologists": "/ɛntəmˈɒləd‍ʒˌɪsts/",
    "entomology": "/ɛntəmˈɒləd‍ʒi/",
    "entourage": "/ˈɒntʊɹˌɑːʒ/",
    "entourages": "/ˈɒntʊɹˌɑːʒɪz/",
    "entrails": "/ˈɛntɹe‍ɪlz/",
    "entranced": "/ɛntɹˈɑːnst/",
    "entranceway": "/ˈɛntɹənswˌe‍ɪ/",
    "entrancing": "/ɛntɹˈɑːnsɪŋ/",
    "entrant": "/ˈɛntɹənt/",
    "entrants": "/ˈɛntɹənts/",
    "entrap": "/ɛntɹˈæp/",
    "entrapment": "/ɛntɹˈæpmənt/",
    "entrapped": "/ɛntɹˈæpt/",
    "entreated": "/ɛntɹˈiːtɪd/",
    "entreat": "/ɛntɹˈiːt/",
    "entreaties": "/ɛntɹˈiːtɪz/",
    "entreats": "/ɛntɹˈiːts/",
    "entreaty": "/ɛntɹˈiːti/",
    "entrechat": "/ˈɒntɹɪt‍ʃˌæt/",
    "entrenched": "/ɛntɹˈɛnt‍ʃt/",
    "entrench": "/ɛntɹˈɛnt‍ʃ/",
    "entrenches": "/ɛntɹˈɛnt‍ʃɪz/",
    "entrenching": "/ɛntɹˈɛnt‍ʃɪŋ/",
    "entrenchment": "/ɛntɹˈɛnt‍ʃmənt/",
    "entrenchments": "/ɛntɹˈɛnt‍ʃmənts/",
    "entrepreneurialism": "/ˌɒntɹɪpɹˈɛnjuːɹˌɪəlˌɪzəm/",
    "entrepreneurially": "/ˌɒntɹɪpɹɪnjˈuːɹɪəli/",
    "entrepreneurial": "/ˌɒntɹɪpɹɪnjˈuːɹɪəl/",
    "entrepreneurism": "/ˌɒntɹɪpɹˈɛnjuːɹəɹˌɪzəm/",
    "entrepreneur": "/ˌɒntɹɪpɹɪnˈɜː/",
    "entrepreneurship": "/ˌɒntɹɪpɹɪnˈɜːʃɪp/",
    "entrepreneurs": "/ˌɒntɹɪpɹɪnˈɜːz/",
    "entries": "/ˈɛntɹɪz/",
    "entropy": "/ˈɛntɹəpi/",
    "entrusted": "/ɛntɹˈʌstɪd/",
    "entrust": "/ɛntɹˈʌst/",
    "entrusting": "/ɛntɹˈʌstɪŋ/",
    "entrusts": "/ɛntɹˈʌsts/",
    "entry": "/ˈɛntɹi/",
    "entryway": "/ˈɛntɹɪwˌe‍ɪ/",
    "entwined": "/ɛntwˈa‍ɪnd/",
    "entwine": "/ɛntwˈa‍ɪn/",
    "entwining": "/ɛntwˈa‍ɪnɪŋ/",
    "enumerated": "/ɪnjˈuːməɹˌe‍ɪtɪd/",
    "enumerate": "/ɪnjˈuːməɹˌe‍ɪt/",
    "enumeration": "/ɪnjˌuːməɹˈe‍ɪʃən/",
    "enunciated": "/ɪnˈʌnsɪˌe‍ɪtɪd/",
    "enunciate": "/ɪnˈʌnsɪˌe‍ɪt/",
    "enunciating": "/ɪnˈʌnsɪˌe‍ɪtɪŋ/",
    "enunciation": "/ɪnˌʌnsɪˈe‍ɪʃən/",
    "enure": "/ɪnjˈɐ/",
    "enuresis": "/ɪnjʊɹˈiːsɪs/",
    "enveloped": "/ɛnvˈɛləpt/",
    "enveloping": "/ɛnvˈɛləpɪŋ/",
    "envelops": "/ɛnvˈɛləps/",
    "enviable": "/ˈɛnvɪəbə‍l/",
    "enviably": "/ˈɛnvɪəbli/",
    "envied": "/ˈɛnvɪd/",
    "envies": "/ˈɛnvɪz/",
    "envious": "/ˈɛnvɪəs/",
    "enviously": "/ˈɛnvɪəsli/",
    "environ": "/ɛnvˈa‍ɪɹən/",
    "environmental": "/ɛnvˌa‍ɪɹənmˈɛntə‍l/",
    "environmentalism": "/ɛnvˌa‍ɪɹənmˈɛntəlˌɪzəm/",
    "environmentalist": "/ɛnvˌa‍ɪɹənmˈɛntəlˌɪst/",
    "environmentalists": "/ɛnvˌa‍ɪɹənmˈɛntəlˌɪsts/",
    "environmentally": "/ɛnvˌa‍ɪɹənmˈɛntə‍li/",
    "environment": "/ɛnvˈa‍ɪɹənmənt/",
    "environments": "/ɛnvˈa‍ɪɹənmənts/",
    "environs": "/ɛnvˈa‍ɪɹənz/",
    "envisaged": "/ɛnvˈɪsɪd‍ʒd/",
    "envisage": "/ɛnvˈɪsɪd‍ʒ/",
    "envisages": "/ɛnvˈɪsɪd‍ʒɪz/",
    "envisaging": "/ɛnvˈɪsɪd‍ʒɪŋ/",
    "envisioned": "/ɛnvˈɪʒənd/",
    "envision": "/ɛnvˈɪʒən/",
    "envisioning": "/ɛnvˈɪʒənɪŋ/",
    "envisions": "/ɛnvˈɪʒənz/",
    "envoi": "/ɛnvˈɔ‍ɪ/",
    "envoy": "/ˈɛnvɔ‍ɪ/",
    "envoys": "/ˈɛnvɔ‍ɪz/",
    "envy": "/ˈɛnvi/",
    "envying": "/ˈɛnvɪɪŋ/",
    "enwrapped": "/ɛnɹˈæpt/",
    "enzymatic": "/ˌɛnzɪmˈætɪk/",
    "enzyme": "/ˈɛnza‍ɪm/",
    "enzymes": "/ˈɛnza‍ɪmz/",
    "eon": "/ˈiːɒn/",
    "eons": "/ˈiːɒnz/",
    "eosinophils": "/ˈiːəsˌɪnəfˌɪlz/",
    "epaulette": "/ˌɛpəlˈɛt/",
    "epaulettes": "/ˌɛpəlˈɛts/",
    "epergne": "/ˈɛpəɡni/",
    "epergnes": "/ˈɛpəɡnɪz/",
    "ephedrine": "/ˈɛfɪdɹˌiːn/",
    "ephemera": "/ɪfˈɛməɹɐ/",
    "ephemeral": "/ɪfˈɛməɹə‍l/",
    "epically": "/ˈɛpɪkli/",
    "epicene": "/ˈɛpɪsˌiːn/",
    "epicentre": "/ˈɛpɪsəntɐ/",
    "epicentres": "/ˈɛpɪsəntəz/",
    "epic": "/ˈɛpɪk/",
    "epics": "/ˈɛpɪks/",
    "epicurean": "/ˈɛpɪkjˌʊɹi‍ən/",
    "epicureans": "/ˈɛpɪkjˌʊɹi‍ənz/",
    "epicure": "/ˈɛpɪkjˌɔː/",
    "epicures": "/ˈɛpɪkjˌɔːz/",
    "epicycles": "/ˈɛpɪsˌa‍ɪkə‍lz/",
    "epidemic": "/ˌɛpɪdˈɛmɪk/",
    "epidemics": "/ˌɛpɪdˈɛmɪks/",
    "epidemiological": "/ˌɛpɪdˌɛmɪəlˈɒd‍ʒɪkə‍l/",
    "epidemiologist": "/ˌɛpɪdˌɛmɪˈɒləd‍ʒˌɪst/",
    "epidemiologists": "/ˌɛpɪdˌɛmɪˈɒləd‍ʒˌɪsts/",
    "epidemiology": "/ˌɛpɪdˌɛmɪˈɒləd‍ʒi/",
    "epidermal": "/ˌɛpɪdˈɜːmə‍l/",
    "epidermis": "/ˌɛpɪdˈɜːmɪs/",
    "epidural": "/ˈɛpɪdjˌɔːɹə‍l/",
    "epidurals": "/ˈɛpɪdjˌɔːɹə‍lz/",
    "epigastrium": "/ˌɛpɪɡˈɑːstɹi‍əm/",
    "epiglottis": "/ˌɛpɪɡlˈɒtiz/",
    "epigram": "/ˈɛpɪɡɹˌæm/",
    "epigrams": "/ˈɛpɪɡɹˌæmz/",
    "epigraph": "/ˈɛpɪɡɹˌæf/",
    "epigraphic": "/ˌɛpɪɡɹˈæfɪk/",
    "epilepsy": "/ˈɛpɪlˌɛpsi/",
    "epileptic": "/ˌɛpɪlˈɛptɪk/",
    "epileptics": "/ˌɛpɪlˈɛptɪks/",
    "epilogue": "/ˈɛpɪlˌɒɡ/",
    "epinephrine": "/ˈɛpɪnˌɛfɹiːn/",
    "epiphanies": "/ɪpˈɪfənˌɪz/",
    "epiphany": "/ɪpˈɪfənˌi/",
    "epiphysis": "/ɛpˈɪfəsˌɪs/",
    "epiphytes": "/ˈɛpɪfˌa‍ɪts/",
    "episcopalian": "/ɪpˌɪskəpˈe‍ɪli‍ən/",
    "episcopal": "/ɪpˈɪskɒpə‍l/",
    "episcopate": "/ɪpˈɪskəpˌe‍ɪt/",
    "episiotomy": "/ˌɛpɪsɪˈɒtəmi/",
    "episode": "/ˈɛpɪsˌə‍ʊd/",
    "episodes": "/ˈɛpɪsˌə‍ʊdz/",
    "episodically": "/ˌɛpɪsˈɒdɪkli/",
    "episodic": "/ˌɛpɪsˈɒdɪk/",
    "epistemology": "/ɪpˌɪstɪmˈɒləd‍ʒi/",
    "epistle": "/ɪpˈɪsə‍l/",
    "epistles": "/ɪpˈɪsə‍lz/",
    "epistolary": "/ɪpɪstˈə‍ʊləɹi/",
    "epitaph": "/ˈɛpɪtˌæf/",
    "epitaphs": "/ˈɛpɪtˌæfz/",
    "epithelium": "/ˌɛpɪθˈiːli‍əm/",
    "epithet": "/ˈɛpɪθɪt/",
    "epithets": "/ˈɛpɪθɪts/",
    "epitome": "/ɪpˈɪtəmˌi/",
    "epitomised": "/ɛpˈɪtəmˌa‍ɪzd/",
    "epitomise": "/ɛpˈɪtəmˌa‍ɪz/",
    "epitomises": "/ɛpˈɪtəmˌa‍ɪzɪz/",
    "epitomising": "/ɛpˈɪtəmˌa‍ɪzɪŋ/",
    "epoch": "/ˈɛpɒk/",
    "epochs": "/ˈɛpɒkz/",
    "eponymous": "/ɛpˈɒnɪməs/",
    "eponyms": "/ˈɛpənˌɪmz/",
    "epos": "/ˈiːpə‍ʊz/",
    "epoxy": "/ɪpˈɒksi/",
    "epsilon": "/ˈɛpsɪlən/",
    "equable": "/ˈɛkəbə‍l/",
    "equal": "/ˈiːkwə‍l/",
    "equalisation": "/ˌiːkwəla‍ɪzˈe‍ɪʃən/",
    "equalised": "/ˈiːkwəlˌa‍ɪzd/",
    "equalise": "/ˈiːkwəlˌa‍ɪz/",
    "equaliser": "/ˈiːkwəlˌa‍ɪzɐ/",
    "equalisers": "/ˈiːkwəlˌa‍ɪzəz/",
    "equalises": "/ˈiːkwəlˌa‍ɪzɪz/",
    "equalising": "/ˈiːkwəlˌa‍ɪzɪŋ/",
    "equalities": "/iːkwˈɒlɪtiz/",
    "equality": "/iːkwˈɒlɪti/",
    "equalled": "/ˈiːkwə‍ld/",
    "equalling": "/ˈiːkwə‍lˌɪŋ/",
    "equally": "/ˈiːkwə‍li/",
    "equals": "/ˈiːkwə‍lz/",
    "equanimity": "/ˌiːkwɐnˈɪmɪti/",
    "equated": "/ɪkwˈe‍ɪtɪd/",
    "equate": "/ɪkwˈe‍ɪt/",
    "equates": "/ɪkwˈe‍ɪts/",
    "equating": "/ɪkwˈe‍ɪtɪŋ/",
    "equation": "/ɪkwˈe‍ɪʒən/",
    "equations": "/ɪkwˈe‍ɪʒənz/",
    "equatorial": "/ɪkwɐtˈɔːɹɪəl/",
    "equator": "/ɪkwˈe‍ɪtɐ/",
    "equators": "/ɪkwˈe‍ɪtəz/",
    "equerries": "/ˈɛkwəɹɪz/",
    "equerry": "/ˈɛkwəɹi/",
    "equestrian": "/ɛkwˈɛstɹi‍ən/",
    "equestrianism": "/ˈɛkwɪstɹˌi‍ənɪzəm/",
    "equestrians": "/ɛkwˈɛstɹi‍ənz/",
    "equidistant": "/ˌiːkwɪdˈɪstənt/",
    "equilateral": "/ˌiːkwɪlˈætəɹə‍l/",
    "equilibrium": "/ˌiːkwɪlˈɪbɹi‍əm/",
    "equine": "/ˈɛkwa‍ɪn/",
    "equines": "/ˈɛkwa‍ɪnz/",
    "equinox": "/ˈɛkwɪnˌɒks/",
    "equinoxes": "/ˈɛkwɪnˌɒksɪz/",
    "equipage": "/ˈɛkwɪpˌɪd‍ʒ/",
    "equip": "/ɪkwˈɪp/",
    "equipment": "/ɪkwˈɪpmənt/",
    "equipments": "/ɪkwˈɪpmənts/",
    "equipped": "/ɪkwˈɪpt/",
    "equipping": "/ɪkwˈɪpɪŋ/",
    "equips": "/ɪkwˈɪps/",
    "equisetum": "/ˌiːkwɪsˈɛtəm/",
    "equitable": "/ˈɛkwɪtəbə‍l/",
    "equitably": "/ˈɛkwɪtəbli/",
    "equities": "/ˈɛkwɪtiz/",
    "equity": "/ˈɛkwɪti/",
    "equivalence": "/ɪkwˈɪvələns/",
    "equivalent": "/ɪkwˈɪvələnt/",
    "equivalents": "/ɪkwˈɪvələnts/",
    "equivocal": "/ɪkwˈɪvəkə‍l/",
    "equivocally": "/ɪkwˈɪvəkə‍li/",
    "equivocated": "/ɪkwˈɪvəkˌe‍ɪtɪd/",
    "equivocate": "/ɪkwˈɪvəkˌe‍ɪt/",
    "equivocates": "/ɪkwˈɪvəkˌe‍ɪts/",
    "equivocating": "/ɪkwˈɪvəkˌe‍ɪtɪŋ/",
    "equivocation": "/ɪkwˌɪvəkˈe‍ɪʃən/",
    "equivocator": "/ɪkwˈɪvəkˌe‍ɪtɐ/",
    "er": "/ˈɜː/",
    "eradicate": "/ɪɹˈædɪkˌe‍ɪt/",
    "eradicated": "/ɪɹˈædɪkˌe‍ɪtɪd/",
    "eradicates": "/ɪɹˈædɪkˌe‍ɪts/",
    "eradicating": "/ɪɹˈædɪkˌe‍ɪtɪŋ/",
    "eradication": "/ɪɹˌædɪkˈe‍ɪʃən/",
    "era": "/ˈi‍əɹɐ/",
    "erasable": "/ɪɹˈe‍ɪzəbə‍l/",
    "erased": "/ɪɹˈe‍ɪzd/",
    "erase": "/ɪɹˈe‍ɪz/",
    "eraser": "/ɪɹˈe‍ɪzɐ/",
    "erasers": "/ɪɹˈe‍ɪzəz/",
    "erases": "/ɪɹˈe‍ɪzɪz/",
    "eras": "/ˈi‍əɹəz/",
    "erasing": "/ɪɹˈe‍ɪzɪŋ/",
    "erasure": "/ɪɹˈe‍ɪʒɐ/",
    "erbium": "/ˈɜːbi‍əm/",
    "erected": "/ɪɹˈɛktɪd/",
    "erect": "/ɪɹˈɛkt/",
    "erectile": "/ɪɹˈɛkta‍ɪl/",
    "erecting": "/ɪɹˈɛktɪŋ/",
    "erection": "/ɪɹˈɛkʃən/",
    "erections": "/ɪɹˈɛkʃənz/",
    "erector": "/ɪɹˈɛktɐ/",
    "erectors": "/ɪɹˈɛktəz/",
    "erects": "/ɪɹˈɛkts/",
    "ere": "/ˈe‍ə/",
    "eremite": "/ɪɹˈɛma‍ɪt/",
    "erg": "/ˈɜːɡ/",
    "ergo": "/ˈɜːɡə‍ʊ/",
    "ergonomically": "/ˌɜːɡənˈɒmɪkli/",
    "ergonomic": "/ˌɜːɡənˈɒmɪk/",
    "ergonomics": "/ˌɜːɡənˈɒmɪks/",
    "ergot": "/ˈɜːɡət/",
    "ergotism": "/ˈɜːɡətˌɪzəm/",
    "ergs": "/ˈɜːɡz/",
    "ericaceous": "/ˌɛɹɪkˈe‍ɪʃəs/",
    "erigeron": "/ˈɛɹɪd‍ʒəɹən/",
    "eristic": "/ɛɹˈɪstɪk/",
    "erk": "/ˈɜːk/",
    "ermine": "/ˈɜːmɪn/",
    "ermines": "/ˈɜːmɪnz/",
    "erne": "/ˈɜːn/",
    "eroded": "/ɪɹˈə‍ʊdɪd/",
    "erode": "/ɪɹˈə‍ʊd/",
    "erodes": "/ɪɹˈə‍ʊdz/",
    "eroding": "/ɪɹˈə‍ʊdɪŋ/",
    "erogenous": "/ɪɹˈɒd‍ʒənəs/",
    "erosional": "/ɪɹˈə‍ʊʒənə‍l/",
    "erosion": "/ɪɹˈə‍ʊʒən/",
    "erosive": "/ɪɹˈə‍ʊsɪv/",
    "erotically": "/ɪɹˈɒtɪkli/",
    "erotica": "/ɪɹˈɒtɪkɐ/",
    "eroticism": "/ɪɹˈɒtɪsˌɪzəm/",
    "erotic": "/ɪɹˈɒtɪk/",
    "erotomania": "/ɪɹˌə‍ʊtəmˈe‍ɪni‍ə/",
    "err": "/ˈɜː/",
    "errand": "/ˈɛɹənd/",
    "errands": "/ˈɛɹəndz/",
    "errant": "/ˈɛɹənt/",
    "erratically": "/ɛɹˈætɪkli/",
    "erratic": "/ɛɹˈætɪk/",
    "erratum": "/ɛɹˈɑːtəm/",
    "erred": "/ˈɜːd/",
    "erring": "/ˈɜːɹɪŋ/",
    "erroneous": "/ɛɹˈə‍ʊni‍əs/",
    "erroneously": "/ɛɹˈə‍ʊni‍əsli/",
    "error": "/ˈɛɹɐ/",
    "errors": "/ˈɛɹəz/",
    "errs": "/ˈɜːz/",
    "ersatz": "/ˈɜːsæts/",
    "erst": "/ˈɜːst/",
    "erstwhile": "/ˈɜːstwa‍ɪl/",
    "erudite": "/ˈɛɹuːdˌa‍ɪt/",
    "erudition": "/ˌɛɹuːdˈɪʃən/",
    "erupted": "/ɪɹˈʌptɪd/",
    "erupting": "/ɪɹˈʌptɪŋ/",
    "eruption": "/ɪɹˈʌpʃən/",
    "eruptions": "/ɪɹˈʌpʃənz/",
    "eruptive": "/ɪɹˈʌptɪv/",
    "erupt": "/ɪɹˈʌpt/",
    "erupts": "/ɪɹˈʌpts/",
    "erythema": "/ˈɜːɹɪθəmɐ/",
    "erythrocytes": "/ɜːɹˈɪθɹəsˌa‍ɪts/",
    "erythromycin": "/ˈɜːɹɪθɹˌɒmɪsˌɪn/",
    "escalade": "/ˈɛskɐlˌe‍ɪd/",
    "escalated": "/ˈɛskɐlˌe‍ɪtɪd/",
    "escalate": "/ˈɛskɐlˌe‍ɪt/",
    "escalates": "/ˈɛskɐlˌe‍ɪts/",
    "escalating": "/ˈɛskɐlˌe‍ɪtɪŋ/",
    "escalation": "/ˌɛskɐlˈe‍ɪʃən/",
    "escalations": "/ˌɛskɐlˈe‍ɪʃənz/",
    "escalator": "/ˈɛskɐlˌe‍ɪtɐ/",
    "escalators": "/ˈɛskɐlˌe‍ɪtəz/",
    "escallop": "/ɛskˈɑːləp/",
    "escalope": "/ˈɛskɐlˌə‍ʊp/",
    "escalopes": "/ˈɛskɐlˌə‍ʊps/",
    "escapade": "/ˈɛskɐpˌe‍ɪd/",
    "escapades": "/ˈɛskɐpˌe‍ɪdz/",
    "escaped": "/ɛskˈe‍ɪpt/",
    "escapee": "/ɛskˈæpiː/",
    "escapees": "/ɛskˈæpiːz/",
    "escape": "/ɛskˈe‍ɪp/",
    "escapement": "/ɛskˈe‍ɪpmənt/",
    "escapements": "/ɛskˈe‍ɪpmənts/",
    "escaper": "/ɛskˈe‍ɪpɐ/",
    "escapes": "/ɛskˈe‍ɪps/",
    "escaping": "/ɛskˈe‍ɪpɪŋ/",
    "escapism": "/ɛskˈe‍ɪpɪzəm/",
    "escapist": "/ɛskˈe‍ɪpɪst/",
    "escapologist": "/ˌɛskɐpˈɒləd‍ʒˌɪst/",
    "escapology": "/ˌɛskɐpˈɒləd‍ʒi/",
    "escargot": "/ɪskˈɑːɡə‍ʊ/",
    "escargots": "/ɪskˈɑːɡə‍ʊs/",
    "escarole": "/ˈɛskəɹˌə‍ʊl/",
    "escarpment": "/ɪskˈɑːpmənt/",
    "escarpments": "/ɪskˈɑːpmənts/",
    "eschatology": "/ˌɛʃɐtˈɒləd‍ʒi/",
    "escheat": "/ˈɛʃiːt/",
    "eschewed": "/ɪst‍ʃˈuːd/",
    "eschewing": "/ɪst‍ʃˈuːɪŋ/",
    "eschews": "/ɪst‍ʃˈuːz/",
    "eschew": "/ɪst‍ʃˈuː/",
    "escorted": "/ɛskˈɔːtɪd/",
    "escorting": "/ɛskˈɔːtɪŋ/",
    "escritoire": "/ˈɛskɹɪtwˌɑː/",
    "escrow": "/ˈɛskɹə‍ʊ/",
    "escudo": "/ɛskjˈuːdə‍ʊ/",
    "escutcheon": "/ɛskˈʌt‍ʃən/",
    "escutcheons": "/ɛskˈʌt‍ʃənz/",
    "es": "/ˈiːz/",
    "esoteric": "/ˌɛsə‍ʊtˈɛɹɪk/",
    "espadrille": "/ɛspˈædɹɪl/",
    "espadrilles": "/ɛspˈædɹɪlz/",
    "espagnole": "/ɛspˈæɡnə‍ʊl/",
    "espaliered": "/ɛspˈæli‍əd/",
    "espalier": "/ɛspˈæliɐ/",
    "espaliers": "/ɛspˈæli‍əz/",
    "especially": "/ɪspˈɛʃə‍lˌi/",
    "especial": "/ɪspˈɛʃə‍l/",
    "espied": "/ɛspˈa‍ɪd/",
    "espionage": "/ˈɛspɪənˌɑːʒ/",
    "esplanade": "/ˈɛsplɐnˌe‍ɪd/",
    "espoused": "/ɛspˈa‍ʊsd/",
    "espouse": "/ɛspˈa‍ʊs/",
    "espouses": "/ɛspˈa‍ʊsɪz/",
    "espousing": "/ɛspˈa‍ʊsɪŋ/",
    "espresso": "/ɛspɹˈɛsə‍ʊ/",
    "espressos": "/ɛspɹˈɛsə‍ʊz/",
    "esprit": "/ɛspɹˈɪt/",
    "espy": "/ɛspˈa‍ɪ/",
    "esquire": "/ˈɛskwa‍ɪ‍ə/",
    "essayed": "/ˈɛse‍ɪd/",
    "essayist": "/ˈɛse‍ɪˌɪst/",
    "esse": "/ˈɛs/",
    "essence": "/ˈɛsəns/",
    "essences": "/ˈɛsənsɪz/",
    "essentially": "/ɪsˈɛnʃə‍lˌi/",
    "essential": "/ɪsˈɛnʃə‍l/",
    "essentials": "/ɪsˈɛnʃə‍lz/",
    "established": "/ɪstˈæblɪʃt/",
    "establishes": "/ɪstˈæblɪʃɪz/",
    "establishing": "/ɪstˈæblɪʃɪŋ/",
    "establishments": "/ɪstˈæblɪʃmənts/",
    "establishment": "/ɪstˈæblɪʃmənt/",
    "establish": "/ɪstˈæblɪʃ/",
    "estancia": "/ˈɛstɑːnʃɐ/",
    "estates": "/ɪstˈe‍ɪts/",
    "estate": "/ɪstˈe‍ɪt/",
    "esteemed": "/ɛstˈiːmd/",
    "esteem": "/ɛstˈiːm/",
    "esteems": "/ɛstˈiːmz/",
    "ester": "/ˈɛstɐ/",
    "esters": "/ˈɛstəz/",
    "esthetic": "/ɛsθˈɛtɪk/",
    "estimable": "/ˈɛstɪməbə‍l/",
    "estimated": "/ˈɛstɪmˌe‍ɪtɪd/",
    "estimating": "/ˈɛstɪmˌe‍ɪtɪŋ/",
    "estimation": "/ˌɛstɪmˈe‍ɪʃən/",
    "estimations": "/ˌɛstɪmˈe‍ɪʃənz/",
    "estimator": "/ˈɛstɪmˌe‍ɪtɐ/",
    "estragon": "/ˈɛstɹəɡən/",
    "estranged": "/ɛstɹˈe‍ɪnd‍ʒd/",
    "estrange": "/ɛstɹˈe‍ɪnd‍ʒ/",
    "estrangement": "/ɛstɹˈe‍ɪnd‍ʒmənt/",
    "estranging": "/ˈɛstɹe‍ɪnd‍ʒˌɪŋ/",
    "estuaries": "/ˈɛstjuːəɹˌiz/",
    "estuarine": "/ˈɛstjuːˌɑːɹiːn/",
    "estuary": "/ˈɛstjuːəɹˌi/",
    "etched": "/ˈɛt‍ʃt/",
    "etcher": "/ˈɛt‍ʃɐ/",
    "etches": "/ˈɛt‍ʃɪz/",
    "etch": "/ˈɛt‍ʃ/",
    "etching": "/ˈɛt‍ʃɪŋ/",
    "etchings": "/ˈɛt‍ʃɪŋz/",
    "eternally": "/ɪtˈɜːnə‍li/",
    "eternal": "/ɪtˈɜːnə‍l/",
    "eterne": "/ɪtˈɜːn/",
    "eternities": "/ɪtˈɜːnɪtiz/",
    "eternity": "/ɪtˈɜːnɪti/",
    "ethane": "/ˈiːθe‍ɪn/",
    "ethanol": "/ˈɛθɐnˌɒl/",
    "ethene": "/ˈiːθiːn/",
    "ethereal": "/iːθˈi‍əɹɪə‍l/",
    "etherised": "/ˈiːθəɹˌa‍ɪzd/",
    "ether": "/ˈiːθɐ/",
    "ethical": "/ˈɛθɪkə‍l/",
    "ethically": "/ˈɛθɪkli/",
    "ethic": "/ˈɛθɪk/",
    "ethicist": "/ˈɛθɪsˌɪst/",
    "ethics": "/ˈɛθɪks/",
    "ethnically": "/ˈɛθnɪkli/",
    "ethnic": "/ˈɛθnɪk/",
    "ethnicity": "/ɛθnˈɪsɪti/",
    "ethnics": "/ˈɛθnɪks/",
    "ethnocentrically": "/ˌɛθnə‍ʊsˈɛntɹɪkli/",
    "ethnographer": "/ɛθnˈɒɡɹəfɐ/",
    "ethnographers": "/ɛθnˈɒɡɹəfəz/",
    "ethnographic": "/ˌɛθnəɡɹˈæfɪk/",
    "ethnography": "/ɛθnˈɒɡɹəfi/",
    "ethnology": "/ɛθnˈɒləd‍ʒi/",
    "ethology": "/iːθˈɒləd‍ʒi/",
    "ethos": "/ˈiːθə‍ʊz/",
    "ethylene": "/ˈɛθɪlˌiːn/",
    "ethyl": "/ˈiːθa‍ɪl/",
    "etiolated": "/ˈɛtɪˌɒle‍ɪtɪd/",
    "etiquette": "/ˈɛtɪkˌɛt/",
    "etna": "/ˈɛtnɐ/",
    "etymological": "/ˌɛtɪməlˈɒd‍ʒɪkə‍l/",
    "etymologically": "/ˌɛtɪməlˈɒd‍ʒɪkli/",
    "etymologies": "/ˌɛtɪmˈɒləd‍ʒɪz/",
    "etymology": "/ˌɛtɪmˈɒləd‍ʒi/",
    "eucalyptus": "/jˈuːkɐlˌɪptəs/",
    "eucharistic": "/jˌuːkəɹˈɪstɪk/",
    "euchre": "/jˈuːkɐ/",
    "euclidean": "/jˌuːkla‍ɪdˈi‍ən/",
    "euclidian": "/juːklˈɪdi‍ən/",
    "eugenicist": "/jˈuːd‍ʒənˌɪsɪst/",
    "eugenicists": "/jˈuːd‍ʒənˌɪsɪsts/",
    "eugenic": "/juːd‍ʒˈɛnɪk/",
    "eugenics": "/juːd‍ʒˈɛnɪks/",
    "eukaryotes": "/jˈuːkɐɹɪˌə‍ʊts/",
    "eukaryotic": "/jˌuːkɐɹɪˈɒtɪk/",
    "eulogies": "/jˈuːləd‍ʒɪz/",
    "eulogised": "/jˈuːləd‍ʒˌa‍ɪzd/",
    "eulogise": "/jˈuːləd‍ʒˌa‍ɪz/",
    "eulogising": "/jˈuːləd‍ʒˌa‍ɪzɪŋ/",
    "eulogy": "/jˈuːləd‍ʒi/",
    "eunuch": "/jˈuːnʌt‍ʃ/",
    "eunuchs": "/jˈuːnʌt‍ʃz/",
    "euonymus": "/jˈuːənˌɪməs/",
    "eupatorium": "/jˌuːpɐtˈɔːɹi‍əm/",
    "euphemism": "/jˈuːfəmˌɪzəm/",
    "euphemisms": "/jˈuːfəmˌɪzəmz/",
    "euphemistically": "/jˌuːfɪmˈɪstɪkli/",
    "euphemistic": "/jˌuːfɪmˈɪstɪk/",
    "euphonious": "/juːfˈə‍ʊnɪəs/",
    "euphonium": "/juːfˈə‍ʊni‍əm/",
    "euphorbia": "/juːfˈɔːbi‍ə/",
    "euphoria": "/juːfˈɔːɹi‍ə/",
    "euphorically": "/juːfˈɒɹɪkli/",
    "euphoric": "/juːfˈɒɹɪk/",
    "eureka": "/juːɹˈiːkɐ/",
    "euro": "/jˈɔːɹə‍ʊ/",
    "europium": "/jɔːɹˈə‍ʊpi‍əm/",
    "euros": "/jˈɔːɹə‍ʊz/",
    "eurythmics": "/juːɹˈɪθmɪks/",
    "euthanasia": "/jˌuːθɐnˈe‍ɪzi‍ə/",
    "euthanize": "/jˈuːθɐnˌa‍ɪz/",
    "evacuated": "/ɪvˈækjuːˌe‍ɪtɪd/",
    "evacuate": "/ɪvˈækjuːˌe‍ɪt/",
    "evacuating": "/ɪvˈækjuːˌe‍ɪtɪŋ/",
    "evacuations": "/ɪvˌækjuːˈe‍ɪʃənz/",
    "evacuation": "/ɪvˌækjuːˈe‍ɪʃən/",
    "evacuees": "/ɪvˈækjuːˌiːz/",
    "evacuee": "/ɪvˈækjuːˌiː/",
    "evaded": "/ɪvˈe‍ɪdɪd/",
    "evaders": "/ɪvˈe‍ɪdəz/",
    "evader": "/ɪvˈe‍ɪdɐ/",
    "evades": "/ɪvˈe‍ɪdz/",
    "evade": "/ɪvˈe‍ɪd/",
    "evading": "/ɪvˈe‍ɪdɪŋ/",
    "evaluated": "/ɪvˈæljuːˌe‍ɪtɪd/",
    "evaluates": "/ɪvˈæljuːˌe‍ɪts/",
    "evaluate": "/ɪvˈæljuːˌe‍ɪt/",
    "evaluating": "/ɪvˈæljuːˌe‍ɪtɪŋ/",
    "evaluations": "/ɪvˌæljuːˈe‍ɪʃənz/",
    "evaluation": "/ɪvˌæljuːˈe‍ɪʃən/",
    "evaluator": "/ɪvˈæljuːˌe‍ɪtɐ/",
    "evanescence": "/ˌɛvənˈɛsəns/",
    "evanescent": "/ˌɛvənˈɛsənt/",
    "evangelicalism": "/ˌiːvɐnd‍ʒˈɛlɪkəlˌɪzəm/",
    "evangelical": "/ˌiːvɐnd‍ʒˈɛlɪkə‍l/",
    "evangelicals": "/ˌiːvɐnd‍ʒˈɛlɪkə‍lz/",
    "evangelisation": "/ɪvˌænd‍ʒɪla‍ɪzˈe‍ɪʃən/",
    "evangelise": "/ɪvˈænd‍ʒɪlˌa‍ɪz/",
    "evangelising": "/ɪvˈænd‍ʒɪlˌa‍ɪzɪŋ/",
    "evangelism": "/ɪvˈænd‍ʒɪlˌɪzəm/",
    "evangelistic": "/ɪvˌænd‍ʒɪlˈɪstɪk/",
    "evangelists": "/ɪvˈænd‍ʒɪlˌɪsts/",
    "evangelist": "/ɪvˈænd‍ʒɪlˌɪst/",
    "evaporated": "/ɪvˈæpəɹˌe‍ɪtɪd/",
    "evaporates": "/ɪvˈæpəɹˌe‍ɪts/",
    "evaporate": "/ɪvˈæpəɹˌe‍ɪt/",
    "evaporating": "/ɪvˈæpəɹˌe‍ɪtɪŋ/",
    "evaporation": "/ɪvˌæpəɹˈe‍ɪʃən/",
    "evaporator": "/ɪvˈæpɔːɹˌe‍ɪtɐ/",
    "evapotranspiration": "/ɪvˌæpətɹˌænspəɹˈe‍ɪʃən/",
    "evasions": "/ɪvˈe‍ɪʒənz/",
    "evasion": "/ɪvˈe‍ɪʒən/",
    "evasively": "/ɪvˈe‍ɪsɪvli/",
    "evasiveness": "/ɪvˈe‍ɪsɪvnəs/",
    "evasive": "/ɪvˈe‍ɪsɪv/",
    "eve": "/ˈiːv/",
    "evened": "/ˈiːvənd/",
    "evenings": "/ˈiːvnɪŋz/",
    "even": "/ˈiːvən/",
    "evenly": "/ˈiːvənli/",
    "evenness": "/ˈiːvənnəs/",
    "evens": "/ˈiːvənz/",
    "evensong": "/ˈiːvənsˌɒŋ/",
    "eventful": "/ɪvˈɛntfə‍l/",
    "eventide": "/ɪvˈɛnta‍ɪd/",
    "eventing": "/ɪvˈɛntɪŋ/",
    "events": "/ɪvˈɛnts/",
    "eventualities": "/ɪvˌɛnt‍ʃuːˈælɪtiz/",
    "eventuality": "/ɪvˌɛnt‍ʃuːˈælɪti/",
    "eventually": "/ɪvˈɛnt‍ʃuːə‍li/",
    "eventual": "/ɪvˈɛnt‍ʃuːə‍l/",
    "event": "/ɪvˈɛnt/",
    "ever": "/ˈɛvɐ/",
    "everglade": "/ˈɛvəɡlˌe‍ɪd/",
    "everglades": "/ˈɛvəɡlˌe‍ɪdz/",
    "evergreen": "/ˈɛvəɡɹˌiːn/",
    "evergreens": "/ˈɛvəɡɹˌiːnz/",
    "everlasting": "/ˌɛvəlˈɑːstɪŋ/",
    "everlastingly": "/ˌɛvəlˈɑːstɪŋli/",
    "evermore": "/ˌɛvəmˈɔː/",
    "evert": "/ˈɛvət/",
    "everybody": "/ˈɛvɹɪbˌɒdi/",
    "everyday": "/ˈɛvɹɪdˌe‍ɪ/",
    "every": "/ˈɛvɹi/",
    "everyman": "/ˈɛvɹɪmən/",
    "everyone": "/ˈɛvɹɪwˌɒn/",
    "everyplace": "/ˈɛvɹɪplˌe‍ɪs/",
    "everything": "/ˈɛvɹɪθˌɪŋ/",
    "everywhere": "/ˈɛvɹɪwˌe‍ə/",
    "eves": "/ˈiːvz/",
    "evicted": "/ɪvˈɪktɪd/",
    "evicting": "/ɪvˈɪktɪŋ/",
    "evictions": "/ɪvˈɪkʃənz/",
    "eviction": "/ɪvˈɪkʃən/",
    "evicts": "/ɪvˈɪkts/",
    "evict": "/ɪvˈɪkt/",
    "evidenced": "/ˈɛvɪdənst/",
    "evidence": "/ˈɛvɪdəns/",
    "evidences": "/ˈɛvɪdənsɪz/",
    "evidencing": "/ˈɛvɪdənsɪŋ/",
    "evident": "/ˈɛvɪdənt/",
    "evidential": "/ˌɛvɪdˈɛnʃə‍l/",
    "evidentiary": "/ˌɛvɪdˈɛnʃjəɹi/",
    "evidently": "/ˈɛvɪdəntli/",
    "evildoers": "/ˈiːvə‍ldˌuːəz/",
    "evil": "/ˈiːvə‍l/",
    "evillest": "/ˈiːvə‍ləst/",
    "evilly": "/ˈiːvə‍lˌi/",
    "evilness": "/ˈiːvə‍lnəs/",
    "evils": "/ˈiːvə‍lz/",
    "evinces": "/ɪvˈɪnsɪz/",
    "evince": "/ɪvˈɪns/",
    "evincing": "/ɪvˈɪnsɪŋ/",
    "eviscerated": "/ɪvˈɪsəɹˌe‍ɪtɪd/",
    "eviscerate": "/ɪvˈɪsəɹˌe‍ɪt/",
    "eviscerating": "/ɪvˈɪsəɹˌe‍ɪtɪŋ/",
    "evisceration": "/ɪvˌɪsəɹˈe‍ɪʃən/",
    "evitable": "/ˈɛvɪtəbə‍l/",
    "evocations": "/ɪvəkˈe‍ɪʃənz/",
    "evocation": "/ɪvəkˈe‍ɪʃən/",
    "evocatively": "/ɪvˈɒkətˌɪvli/",
    "evocative": "/ɪvˈɒkətˌɪv/",
    "evoked": "/ɪvˈə‍ʊkt/",
    "evokes": "/ɪvˈə‍ʊks/",
    "evoke": "/ɪvˈə‍ʊk/",
    "evoking": "/ɪvˈə‍ʊkɪŋ/",
    "evolutionarily": "/ɪvəlˈuːʃənˈɛɹəli/",
    "evolutionary": "/ɪvəlˈuːʃənəɹi/",
    "evolutionists": "/ɪvəlˈuːʃənˌɪsts/",
    "evolutionist": "/ɪvəlˈuːʃənˌɪst/",
    "evolutions": "/ɪvəlˈuːʃənz/",
    "evolution": "/ɪvəlˈuːʃən/",
    "evolved": "/ɪvˈɒlvd/",
    "evolvement": "/ɪvˈɒlvmənt/",
    "evolves": "/ɪvˈɒlvz/",
    "evolve": "/ɪvˈɒlv/",
    "evolving": "/ɪvˈɒlvɪŋ/",
    "ewer": "/jˈuːɐ/",
    "ewers": "/jˈuːəz/",
    "ewes": "/jˈuːz/",
    "exabytes": "/ɛɡzˈæba‍ɪts/",
    "exacerbated": "/ɛɡzˈæsəbˌe‍ɪtɪd/",
    "exacerbate": "/ɛɡzˈæsəbˌe‍ɪt/",
    "exacerbates": "/ɛɡzˈæsəbˌe‍ɪts/",
    "exacerbating": "/ɛɡzˈæsəbˌe‍ɪtɪŋ/",
    "exacerbation": "/ɛɡzˌæsəbˈe‍ɪʃən/",
    "exacted": "/ɛɡzˈæktɪd/",
    "exact": "/ɛɡzˈækt/",
    "exacting": "/ɛɡzˈæktɪŋ/",
    "exactitude": "/ɛɡzˈæktɪtjˌuːd/",
    "exactly": "/ɛɡzˈæktli/",
    "exactness": "/ɛɡzˈæktnəs/",
    "exacts": "/ɛɡzˈækts/",
    "exaggerated": "/ɛɡzˈæd‍ʒəɹˌe‍ɪtɪd/",
    "exaggerate": "/ɛɡzˈæd‍ʒəɹˌe‍ɪt/",
    "exaggerates": "/ɛɡzˈæd‍ʒəɹˌe‍ɪts/",
    "exaggerating": "/ɛɡzˈæd‍ʒəɹˌe‍ɪtɪŋ/",
    "exaggeration": "/ɛɡzˌæd‍ʒəɹˈe‍ɪʃən/",
    "exaggerations": "/ɛɡzˌæd‍ʒəɹˈe‍ɪʃənz/",
    "exaltation": "/ɛɡzɐltˈe‍ɪʃən/",
    "exalted": "/ɛɡzˈɒltɪd/",
    "exalt": "/ɛɡzˈɒlt/",
    "exalting": "/ɛɡzˈɒltɪŋ/",
    "exalts": "/ɛɡzˈɒlts/",
    "exam": "/ɛɡzˈæm/",
    "examination": "/ɛɡzˌæmɪnˈe‍ɪʃən/",
    "examinations": "/ɛɡzˌæmɪnˈe‍ɪʃənz/",
    "examined": "/ɛɡzˈæmɪnd/",
    "examine": "/ɛɡzˈæmɪn/",
    "examiner": "/ɛɡzˈæmɪnɐ/",
    "examiners": "/ɛɡzˈæmɪnəz/",
    "examines": "/ɛɡzˈæmɪnz/",
    "examining": "/ɛɡzˈæmɪnɪŋ/",
    "example": "/ɛɡzˈɑːmpə‍l/",
    "examples": "/ɛɡzˈɑːmpə‍lz/",
    "exams": "/ɛɡzˈæmz/",
    "exasperated": "/ɛɡzˈɑːspəɹˌe‍ɪtɪd/",
    "exasperate": "/ɛɡzˈɑːspəɹˌe‍ɪt/",
    "exasperates": "/ɛɡzˈɑːspəɹˌe‍ɪts/",
    "exasperating": "/ɛɡzˈɑːspəɹˌe‍ɪtɪŋ/",
    "exasperation": "/ɛɡzˌɑːspəɹˈe‍ɪʃən/",
    "excavated": "/ˈɛkskəvˌe‍ɪtɪd/",
    "excavate": "/ˈɛkskəvˌe‍ɪt/",
    "excavates": "/ˈɛkskəvˌe‍ɪts/",
    "excavating": "/ˈɛkskəvˌe‍ɪtɪŋ/",
    "excavation": "/ˌɛkskəvˈe‍ɪʃən/",
    "excavations": "/ˌɛkskəvˈe‍ɪʃənz/",
    "excavator": "/ˈɛkskəvˌe‍ɪtɐ/",
    "excavators": "/ˈɛkskəvˌe‍ɪtəz/",
    "exceeded": "/ɛksˈiːdɪd/",
    "exceed": "/ɛksˈiːd/",
    "exceeding": "/ɛksˈiːdɪŋ/",
    "exceedingly": "/ɛksˈiːdɪŋli/",
    "exceeds": "/ɛksˈiːdz/",
    "excel": "/ɛksˈɛl/",
    "excelled": "/ɛksˈɛld/",
    "excellence": "/ˈɛksələns/",
    "excellencies": "/ˈɛksələnsiz/",
    "excellency": "/ˈɛksələnsi/",
    "excellent": "/ˈɛksələnt/",
    "excellently": "/ˈɛksələntli/",
    "excelling": "/ɛksˈɛlɪŋ/",
    "excels": "/ɛksˈɛlz/",
    "excelsior": "/ɛksˈɛlsjɐ/",
    "excepted": "/ɛksˈɛptɪd/",
    "except": "/ɛksˈɛpt/",
    "excepting": "/ɛksˈɛptɪŋ/",
    "exceptional": "/ɛksˈɛpʃənə‍l/",
    "exceptionally": "/ɛksˈɛpʃənə‍li/",
    "exception": "/ɛksˈɛpʃən/",
    "exceptions": "/ɛksˈɛpʃənz/",
    "excepts": "/ɛksˈɛpts/",
    "excerpt": "/ɛksˈɜːpt/",
    "excerpts": "/ɛksˈɜːpts/",
    "excesses": "/ɛksˈɛsɪz/",
    "excessive": "/ɛksˈɛsɪv/",
    "excessively": "/ɛksˈɛsɪvli/",
    "exchangeable": "/ɛkst‍ʃˈe‍ɪnd‍ʒəbə‍l/",
    "exchanged": "/ɛkst‍ʃˈe‍ɪnd‍ʒd/",
    "exchange": "/ɛkst‍ʃˈe‍ɪnd‍ʒ/",
    "exchanger": "/ɛkst‍ʃˈe‍ɪnd‍ʒɐ/",
    "exchangers": "/ɛkst‍ʃˈe‍ɪnd‍ʒəz/",
    "exchanges": "/ɛkst‍ʃˈe‍ɪnd‍ʒɪz/",
    "exchanging": "/ɛkst‍ʃˈe‍ɪnd‍ʒɪŋ/",
    "exchequer": "/ɛkst‍ʃˈɛkɐ/",
    "excised": "/ɛksˈa‍ɪzd/",
    "exciseman": "/ɛksˈa‍ɪsmən/",
    "excising": "/ɛksˈa‍ɪzɪŋ/",
    "excision": "/ɛksˈɪʒən/",
    "excitability": "/ɛksˌa‍ɪtəbˈɪlɪti/",
    "excitable": "/ɛksˈa‍ɪtəbə‍l/",
    "excitably": "/ɛksˈa‍ɪtəbli/",
    "excitation": "/ɛksɪtˈe‍ɪʃən/",
    "excitations": "/ɛksɪtˈe‍ɪʃənz/",
    "excited": "/ɛksˈa‍ɪtɪd/",
    "excitedly": "/ɛksˈa‍ɪtɪdli/",
    "excite": "/ɛksˈa‍ɪt/",
    "excitement": "/ɛksˈa‍ɪtmənt/",
    "excitements": "/ɛksˈa‍ɪtmənts/",
    "exciter": "/ɛksˈa‍ɪtɐ/",
    "excites": "/ɛksˈa‍ɪts/",
    "exciting": "/ɛksˈa‍ɪtɪŋ/",
    "excitingly": "/ɛksˈa‍ɪtɪŋli/",
    "exclaimed": "/ɛksklˈe‍ɪmd/",
    "exclaim": "/ɛksklˈe‍ɪm/",
    "exclaiming": "/ɛksklˈe‍ɪmɪŋ/",
    "exclaims": "/ɛksklˈe‍ɪmz/",
    "exclamation": "/ɛksklɐmˈe‍ɪʃən/",
    "exclamations": "/ɛksklɐmˈe‍ɪʃənz/",
    "exclave": "/ɛksklˈe‍ɪv/",
    "excluded": "/ɛksklˈuːdɪd/",
    "exclude": "/ɛksklˈuːd/",
    "excludes": "/ɛksklˈuːdz/",
    "excluding": "/ɛksklˈuːdɪŋ/",
    "exclusionary": "/ɛksklˈuːʒənəɹi/",
    "exclusion": "/ɛksklˈuːʒən/",
    "exclusions": "/ɛksklˈuːʒənz/",
    "exclusive": "/ɛksklˈuːsɪv/",
    "exclusively": "/ɛksklˈuːsɪvli/",
    "exclusiveness": "/ɛksklˈuːsɪvnəs/",
    "exclusives": "/ɛksklˈuːsɪvz/",
    "exclusivity": "/ɛkskluːsˈɪvɪti/",
    "excommunicated": "/ɛkskəmjˈuːnɪkˌe‍ɪtɪd/",
    "excommunicate": "/ɛkskəmjˈuːnɪkˌe‍ɪt/",
    "excommunicating": "/ɛkskəmjˈuːnɪkˌe‍ɪtɪŋ/",
    "excommunication": "/ɛkskəmjˌuːnɪkˈe‍ɪʃən/",
    "excommunications": "/ɛkskəmjˌuːnɪkˈe‍ɪʃənz/",
    "excoriated": "/ɛkskˈɔːɹɪˌe‍ɪtɪd/",
    "excoriating": "/ɛkskˈɔːɹɪˌe‍ɪtɪŋ/",
    "excrement": "/ˈɛkskɹɪmənt/",
    "excrescence": "/ɛkskɹˈɛsəns/",
    "excreta": "/ɛkskɹˈɛtɐ/",
    "excreted": "/ɛkskɹˈiːtɪd/",
    "excrete": "/ɛkskɹˈiːt/",
    "excretes": "/ɛkskɹˈiːts/",
    "excreting": "/ɛkskɹˈiːtɪŋ/",
    "excretion": "/ɛkskɹˈɛʃən/",
    "excretions": "/ɛkskɹˈɛʃənz/",
    "excretory": "/ɛkskɹˈɛtəɹˌi/",
    "excruciated": "/ɛkskɹˈuːʃɪˌe‍ɪtɪd/",
    "excruciating": "/ɛkskɹˈuːʃɪˌe‍ɪtɪŋ/",
    "excruciatingly": "/ɛkskɹˈuːʃɪˌe‍ɪtɪŋli/",
    "exculpatory": "/ɛkskˈʌlpətəɹˌi/",
    "excursion": "/ɛkskˈɜːʃən/",
    "excursionists": "/ɛkskˈɜːʃənˌɪsts/",
    "excursions": "/ɛkskˈɜːʃənz/",
    "excusable": "/ɛkskjˈuːsəbə‍l/",
    "excused": "/ɛkskjˈuːsd/",
    "excusing": "/ɛkskjˈuːsɪŋ/",
    "exec": "/ɛɡzˈɛk/",
    "execrable": "/ɛɡzˈɛkɹəbə‍l/",
    "execration": "/ɛɡzɪkɹˈe‍ɪʃən/",
    "execs": "/ɛɡzˈɛks/",
    "executable": "/ˌɛksɪkjˈuːtəbə‍l/",
    "executed": "/ˈɛksɪkjˌuːtɪd/",
    "execute": "/ˈɛksɪkjˌuːt/",
    "executes": "/ˈɛksɪkjˌuːts/",
    "executing": "/ˈɛksɪkjˌuːtɪŋ/",
    "execution": "/ˌɛksɪkjˈuːʃən/",
    "executioner": "/ˌɛksɪkjˈuːʃənɐ/",
    "executioners": "/ˌɛksɪkjˈuːʃənəz/",
    "executions": "/ˌɛksɪkjˈuːʃənz/",
    "executive": "/ɛɡzˈɛkjuːtˌɪv/",
    "executives": "/ɛɡzˈɛkjuːtˌɪvz/",
    "executor": "/ɛɡzˈɛkjuːtɐ/",
    "executors": "/ɛɡzˈɛkjuːtəz/",
    "exegesis": "/ɛɡzɪd‍ʒˈiːsɪs/",
    "ex": "/ˈɛks/",
    "exemplar": "/ɛɡzˈɛmplɐ/",
    "exemplars": "/ɛɡzˈɛmpləz/",
    "exemplary": "/ɛɡzˈɛmpləɹi/",
    "exemplified": "/ɛɡzˈɛmplɪfˌa‍ɪd/",
    "exemplifies": "/ɛɡzˈɛmplɪfˌa‍ɪz/",
    "exemplify": "/ɛɡzˈɛmplɪfˌa‍ɪ/",
    "exemplum": "/ɛɡzˈɛmpləm/",
    "exempted": "/ɛɡzˈɛmptɪd/",
    "exempt": "/ɛɡzˈɛmpt/",
    "exempting": "/ɛɡzˈɛmptɪŋ/",
    "exemption": "/ɛɡzˈɛmpʃən/",
    "exemptions": "/ɛɡzˈɛmpʃənz/",
    "exempts": "/ɛɡzˈɛmpts/",
    "exercised": "/ˈɛksəsˌa‍ɪzd/",
    "exercise": "/ˈɛksəsˌa‍ɪz/",
    "exerciser": "/ˈɛksəsˌa‍ɪzɐ/",
    "exercisers": "/ˈɛksəsˌa‍ɪzəz/",
    "exercises": "/ˈɛksəsˌa‍ɪzɪz/",
    "exercising": "/ˈɛksəsˌa‍ɪzɪŋ/",
    "exerted": "/ɛɡzˈɜːtɪd/",
    "exert": "/ɛɡzˈɜːt/",
    "exerting": "/ɛɡzˈɜːtɪŋ/",
    "exertion": "/ɛɡzˈɜːʃən/",
    "exertions": "/ɛɡzˈɜːʃənz/",
    "exerts": "/ɛɡzˈɜːts/",
    "exes": "/ˈɛksɪz/",
    "exeunt": "/ɛɡzjˈuːnt/",
    "exfoliant": "/ɛksfˈə‍ʊli‍ənt/",
    "exfoliated": "/ɛksfˈə‍ʊlɪˌe‍ɪtɪd/",
    "exfoliate": "/ɛksfˈə‍ʊlɪˌe‍ɪt/",
    "exfoliates": "/ɛksfˈə‍ʊlɪˌe‍ɪts/",
    "exfoliating": "/ɛksfˈə‍ʊlɪˌe‍ɪtɪŋ/",
    "exfoliation": "/ɛksfˈə‍ʊlɪˈe‍ɪʃən/",
    "exfoliator": "/ɛksfˈə‍ʊlɪˌe‍ɪtɐ/",
    "exhalation": "/ɛkshɐlˈe‍ɪʃən/",
    "exhalations": "/ɛkshɐlˈe‍ɪʃənz/",
    "exhaled": "/ɛkshˈe‍ɪld/",
    "exhale": "/ɛkshˈe‍ɪl/",
    "exhales": "/ɛkshˈe‍ɪlz/",
    "exhaling": "/ɛkshˈe‍ɪlɪŋ/",
    "exhausted": "/ɛɡzˈɔːstɪd/",
    "exhaust": "/ɛɡzˈɔːst/",
    "exhausting": "/ɛɡzˈɔːstɪŋ/",
    "exhaustion": "/ɛɡzˈɔːst‍ʃən/",
    "exhaustive": "/ɛɡzˈɔːstɪv/",
    "exhaustively": "/ɛɡzˈɔːstɪvli/",
    "exhausts": "/ɛɡzˈɔːsts/",
    "exhibited": "/ɛɡzˈɪbɪtɪd/",
    "exhibit": "/ɛɡzˈɪbɪt/",
    "exhibiting": "/ɛɡzˈɪbɪtɪŋ/",
    "exhibition": "/ɛksɪbˈɪʃən/",
    "exhibitionism": "/ɛksɪbˈɪʃənˌɪzəm/",
    "exhibitionist": "/ɛksɪbˈɪʃənˌɪst/",
    "exhibitionistic": "/ɛksɪbˈɪʃənˈɪstɪk/",
    "exhibitionists": "/ɛksɪbˈɪʃənˌɪsts/",
    "exhibitions": "/ɛksɪbˈɪʃənz/",
    "exhibitor": "/ɛɡzˈɪbɪtɐ/",
    "exhibitors": "/ɛɡzˈɪbɪtəz/",
    "exhibits": "/ɛɡzˈɪbɪts/",
    "exhilarated": "/ɛɡzˈɪlɐɹˌe‍ɪtɪd/",
    "exhilarates": "/ɛɡzˈɪlɐɹˌe‍ɪts/",
    "exhilarating": "/ɛɡzˈɪlɐɹˌe‍ɪtɪŋ/",
    "exhilaration": "/ɛɡzˌɪlɐɹˈe‍ɪʃən/",
    "exhortation": "/ɛɡzɔːtˈe‍ɪʃən/",
    "exhortations": "/ɛɡzɔːtˈe‍ɪʃənz/",
    "exhorted": "/ɛɡzˈɔːtɪd/",
    "exhort": "/ɛɡzˈɔːt/",
    "exhorting": "/ɛɡzˈɔːtɪŋ/",
    "exhorts": "/ɛɡzˈɔːts/",
    "exhumation": "/ɛɡzjuːmˈe‍ɪʃən/",
    "exhumations": "/ɛɡzjuːmˈe‍ɪʃənz/",
    "exhumed": "/ɛɡzjˈuːmd/",
    "exhume": "/ɛɡzjˈuːm/",
    "exhuming": "/ɛɡzjˈuːmɪŋ/",
    "exigent": "/ɛɡzˈa‍ɪd‍ʒənt/",
    "exiguous": "/ɛɡzˈɪɡjuːəs/",
    "exiled": "/ˈɛɡza‍ɪld/",
    "exile": "/ˈɛɡza‍ɪl/",
    "exiles": "/ˈɛɡza‍ɪlz/",
    "exiling": "/ˈɛɡza‍ɪlɪŋ/",
    "existed": "/ɛɡzˈɪstɪd/",
    "existence": "/ɛɡzˈɪstəns/",
    "existences": "/ɛɡzˈɪstənsɪz/",
    "existent": "/ɛɡzˈɪstənt/",
    "existential": "/ɛɡzɪstˈɛnʃə‍l/",
    "existentialism": "/ɛɡzɪstˈɛnʃɪəlˌɪzəm/",
    "existentialist": "/ɛɡzɪstˈɛnʃɪəlˌɪst/",
    "exist": "/ɛɡzˈɪst/",
    "existing": "/ɛɡzˈɪstɪŋ/",
    "exists": "/ɛɡzˈɪsts/",
    "exited": "/ˈɛɡzɪtɪd/",
    "exit": "/ˈɛɡzɪt/",
    "exiting": "/ˈɛɡzɪtɪŋ/",
    "exits": "/ˈɛɡzɪts/",
    "exodus": "/ˈɛksədəs/",
    "exonerated": "/ɛɡzˈɒnəɹˌe‍ɪtɪd/",
    "exonerate": "/ɛɡzˈɒnəɹˌe‍ɪt/",
    "exonerates": "/ɛɡzˈɒnəɹˌe‍ɪts/",
    "exonerating": "/ɛɡzˈɒnəɹˌe‍ɪtɪŋ/",
    "exoneration": "/ɛɡzə‍ʊnɹˈe‍ɪʃən/",
    "exon": "/ɛɡzˈɒn/",
    "exorbitant": "/ɛɡzˈɔːbɪtənt/",
    "exorbitantly": "/ɛɡzˈɔːbɪtəntli/",
    "exorcised": "/ˈɛksəsˌa‍ɪzd/",
    "exorcise": "/ˈɛksəsˌa‍ɪz/",
    "exorcising": "/ˈɛksəsˌa‍ɪzɪŋ/",
    "exorcism": "/ˈɛksəsˌɪzəm/",
    "exorcisms": "/ˈɛksəsˌɪzəmz/",
    "exorcist": "/ˈɛksəsˌɪst/",
    "exorcists": "/ˈɛksəsˌɪsts/",
    "exoskeleton": "/ˈɛksə‍ʊskˌɛlɪtən/",
    "exoskeletons": "/ˈɛksə‍ʊskˌɛlɪtənz/",
    "exosphere": "/ˈɛksə‍ʊsfˌi‍ə/",
    "exothermic": "/ɛɡzəðˈɜːmɪk/",
    "exotica": "/ɛɡzˈɒtɪkɐ/",
    "exotically": "/ɛɡzˈɒtɪkli/",
    "exotic": "/ɛɡzˈɒtɪk/",
    "exoticism": "/ɛɡzˈɒtɪsˌɪzəm/",
    "exotics": "/ɛɡzˈɒtɪks/",
    "expandable": "/ɛkspˈændəbə‍l/",
    "expanded": "/ɛkspˈændɪd/",
    "expand": "/ɛkspˈænd/",
    "expander": "/ɛkspˈændɐ/",
    "expanding": "/ɛkspˈændɪŋ/",
    "expands": "/ɛkspˈændz/",
    "expanse": "/ɛkspˈæns/",
    "expanses": "/ɛkspˈænsɪz/",
    "expansionary": "/ɛkspˈænʃənəɹi/",
    "expansion": "/ɛkspˈænʃən/",
    "expansionism": "/ɛkspˈænʃənˌɪzəm/",
    "expansionist": "/ɛkspˈænʃənˌɪst/",
    "expansionists": "/ɛkspˈænʃənˌɪsts/",
    "expansions": "/ɛkspˈænʃənz/",
    "expansive": "/ɛkspˈænsɪv/",
    "expansively": "/ɛkspˈænsɪvli/",
    "expansiveness": "/ɛkspˈænsɪvnəs/",
    "expat": "/ɛkspˈæt/",
    "expatriated": "/ɛkspˈætɹɪˌe‍ɪtɪd/",
    "expats": "/ɛkspˈæts/",
    "expectancies": "/ɛkspˈɛktənsɪz/",
    "expectancy": "/ɛkspˈɛktənsi/",
    "expectant": "/ɛkspˈɛktənt/",
    "expectantly": "/ɛkspˈɛktəntli/",
    "expectation": "/ɛkspɪktˈe‍ɪʃən/",
    "expectations": "/ɛkspɪktˈe‍ɪʃənz/",
    "expected": "/ɛkspˈɛktɪd/",
    "expect": "/ɛkspˈɛkt/",
    "expecting": "/ɛkspˈɛktɪŋ/",
    "expectorant": "/ɛkspˈɛktəɹənt/",
    "expectorating": "/ɛkspˈɛktəɹˌe‍ɪtɪŋ/",
    "expects": "/ɛkspˈɛkts/",
    "expedience": "/ɛkspˈiːdi‍əns/",
    "expediency": "/ɛkspˈiːdi‍ənsi/",
    "expedient": "/ɛkspˈiːdi‍ənt/",
    "expedients": "/ɛkspˈiːdi‍ənts/",
    "expedited": "/ˈɛkspədˌa‍ɪtɪd/",
    "expedite": "/ˈɛkspədˌa‍ɪt/",
    "expediter": "/ˈɛkspədˌa‍ɪtɐ/",
    "expediting": "/ˈɛkspədˌa‍ɪtɪŋ/",
    "expeditionary": "/ˌɛkspədˈɪʃənəɹi/",
    "expedition": "/ˌɛkspədˈɪʃən/",
    "expeditions": "/ˌɛkspədˈɪʃənz/",
    "expeditious": "/ˌɛkspədˈɪʃəs/",
    "expeditiously": "/ˌɛkspədˈɪʃəsli/",
    "expel": "/ɛkspˈɛl/",
    "expelled": "/ɛkspˈɛld/",
    "expelling": "/ɛkspˈɛlɪŋ/",
    "expels": "/ɛkspˈɛlz/",
    "expendable": "/ɛkspˈɛndəbə‍l/",
    "expendables": "/ɛkspˈɛndəbə‍lz/",
    "expended": "/ɛkspˈɛndɪd/",
    "expend": "/ɛkspˈɛnd/",
    "expending": "/ɛkspˈɛndɪŋ/",
    "expenditure": "/ɛkspˈɛndɪt‍ʃɐ/",
    "expenditures": "/ɛkspˈɛndɪt‍ʃəz/",
    "expends": "/ɛkspˈɛndz/",
    "expense": "/ɛkspˈɛns/",
    "expenses": "/ɛkspˈɛnsɪz/",
    "expensive": "/ɛkspˈɛnsɪv/",
    "expensively": "/ɛkspˈɛnsɪvli/",
    "experienced": "/ɛkspˈi‍əɹɪənst/",
    "experience": "/ɛkspˈi‍əɹɪəns/",
    "experiences": "/ɛkspˈi‍əɹɪənsɪz/",
    "experiencing": "/ɛkspˈi‍əɹɪənsɪŋ/",
    "experiential": "/ɛkspˌi‍əɹɪˈɛnʃə‍l/",
    "experimental": "/ɛkspˌɛɹɪmˈɛntə‍l/",
    "experimentalism": "/ɛkspˌɛɹɪmˈɛntəlˌɪzəm/",
    "experimentalist": "/ɛkspˌɛɹɪmˈɛntəlˌɪst/",
    "experimentalists": "/ɛkspˌɛɹɪmˈɛntəlˌɪsts/",
    "experimentally": "/ɛkspˌɛɹɪmˈɛntə‍li/",
    "experimentation": "/ɛkspˌɛɹɪməntˈe‍ɪʃən/",
    "experimented": "/ɛkspˈɛɹɪməntɪd/",
    "experiment": "/ɛkspˈɛɹɪmənt/",
    "experimenter": "/ɛkspˈɛɹɪməntɐ/",
    "experimenters": "/ɛkspˈɛɹɪmˌɛntəz/",
    "experimenting": "/ɛkspˈɛɹɪməntɪŋ/",
    "experiments": "/ɛkspˈɛɹɪmənts/",
    "expert": "/ˈɛkspɜːt/",
    "expertise": "/ˌɛkspətˈiːz/",
    "expertly": "/ˈɛkspɜːtli/",
    "experts": "/ˈɛkspɜːts/",
    "expiate": "/ɛkspɪˈe‍ɪt/",
    "expiation": "/ɛkspɪˈe‍ɪʃən/",
    "expiration": "/ɛkspəɹˈe‍ɪʃən/",
    "expired": "/ɛkspˈa‍ɪ‍əd/",
    "expire": "/ɛkspˈa‍ɪ‍ə/",
    "expires": "/ɛkspˈa‍ɪ‍əz/",
    "expiring": "/ɛkspˈa‍ɪ‍əɹɪŋ/",
    "expiry": "/ɛkspˈa‍ɪ‍əɹi/",
    "explainable": "/ɛksplˈe‍ɪnəbə‍l/",
    "explained": "/ɛksplˈe‍ɪnd/",
    "explain": "/ɛksplˈe‍ɪn/",
    "explainer": "/ɛksplˈe‍ɪnɐ/",
    "explaining": "/ɛksplˈe‍ɪnɪŋ/",
    "explains": "/ɛksplˈe‍ɪnz/",
    "explanation": "/ɛksplɐnˈe‍ɪʃən/",
    "explanations": "/ɛksplɐnˈe‍ɪʃənz/",
    "explanatory": "/ɛksplˈænətəɹˌi/",
    "expletive": "/ɛksplˈiːtɪv/",
    "expletives": "/ɛksplˈiːtɪvz/",
    "explicable": "/ɛksplˈɪkəbə‍l/",
    "explicate": "/ɛksplɪkˈe‍ɪt/",
    "explicit": "/ɛksplˈɪsɪt/",
    "explicitly": "/ɛksplˈɪsɪtli/",
    "exploded": "/ɛksplˈə‍ʊdɪd/",
    "explode": "/ɛksplˈə‍ʊd/",
    "exploder": "/ɛksplˈə‍ʊdɐ/",
    "explodes": "/ɛksplˈə‍ʊdz/",
    "exploding": "/ɛksplˈə‍ʊdɪŋ/",
    "exploitable": "/ɛksplˈɔ‍ɪtəbə‍l/",
    "exploitation": "/ɛksplɔ‍ɪtˈe‍ɪʃən/",
    "exploitative": "/ɛksplˈɔ‍ɪtətˌɪv/",
    "exploited": "/ɛksplˈɔ‍ɪtɪd/",
    "exploiter": "/ɛksplˈɔ‍ɪtɐ/",
    "exploiters": "/ɛksplˈɔ‍ɪtəz/",
    "exploiting": "/ɛksplˈɔ‍ɪtɪŋ/",
    "exploitive": "/ɛksplˈɔ‍ɪtɪv/",
    "exploration": "/ɛksplɔːɹˈe‍ɪʃən/",
    "explorations": "/ɛksplɔːɹˈe‍ɪʃənz/",
    "exploratory": "/ɛksplˈɔːɹətəɹˌi/",
    "explored": "/ɛksplˈɔːd/",
    "explore": "/ɛksplˈɔː/",
    "explorer": "/ɛksplˈɔːɹɐ/",
    "explorers": "/ɛksplˈɔːɹəz/",
    "explores": "/ɛksplˈɔːz/",
    "exploring": "/ɛksplˈɔːɹɪŋ/",
    "explosion": "/ɛksplˈə‍ʊʒən/",
    "explosions": "/ɛksplˈə‍ʊʒənz/",
    "explosive": "/ɛksplˈə‍ʊsɪv/",
    "explosively": "/ɛksplˈə‍ʊsɪvli/",
    "explosiveness": "/ɛksplˈə‍ʊsɪvnəs/",
    "explosives": "/ɛksplˈə‍ʊsɪvz/",
    "expo": "/ˈɛkspə‍ʊ/",
    "exponent": "/ɛkspˈə‍ʊnənt/",
    "exponential": "/ˌɛkspənˈɛnʃə‍l/",
    "exponentially": "/ˌɛkspənˈɛnʃə‍lˌi/",
    "exponents": "/ɛkspˈə‍ʊnənts/",
    "exportable": "/ɛkspˈɔːtəbə‍l/",
    "exportation": "/ɛkspɔːtˈe‍ɪʃən/",
    "exported": "/ɛkspˈɔːtɪd/",
    "exporter": "/ɛkspˈɔːtɐ/",
    "exporters": "/ɛkspˈɔːtəz/",
    "exporting": "/ɛkspˈɔːtɪŋ/",
    "exposed": "/ɛkspˈə‍ʊzd/",
    "expos": "/ˈɛkspə‍ʊz/",
    "exposing": "/ɛkspˈə‍ʊzɪŋ/",
    "exposition": "/ɛkspəzˈɪʃən/",
    "expositions": "/ɛkspəzˈɪʃənz/",
    "expostulate": "/ɛkspˈɒstjʊlˌe‍ɪt/",
    "exposure": "/ɛkspˈə‍ʊʒɐ/",
    "exposures": "/ɛkspˈə‍ʊʒəz/",
    "expounded": "/ɛkspˈa‍ʊndɪd/",
    "expound": "/ɛkspˈa‍ʊnd/",
    "expounding": "/ɛkspˈa‍ʊndɪŋ/",
    "expressed": "/ɛkspɹˈɛst/",
    "express": "/ɛkspɹˈɛs/",
    "expresses": "/ɛkspɹˈɛsɪz/",
    "expressible": "/ɛkspɹˈɛsəbə‍l/",
    "expressing": "/ɛkspɹˈɛsɪŋ/",
    "expression": "/ɛkspɹˈɛʃən/",
    "expressionism": "/ɛkspɹˈɛʃənˌɪzəm/",
    "expressionist": "/ɛkspɹˈɛʃənˌɪst/",
    "expressionistic": "/ɛkspɹˈɛʃənˈɪstɪk/",
    "expressionists": "/ɛkspɹˈɛʃənˌɪsts/",
    "expressionless": "/ɛkspɹˈɛʃənləs/",
    "expressions": "/ɛkspɹˈɛʃənz/",
    "expressive": "/ɛkspɹˈɛsɪv/",
    "expressively": "/ɛkspɹˈɛsɪvli/",
    "expressiveness": "/ɛkspɹˈɛsɪvnəs/",
    "expressivity": "/ɛkspɹɪsˈɪvɪti/",
    "expressly": "/ɛkspɹˈɛsli/",
    "expressway": "/ɛkspɹˈɛswe‍ɪ/",
    "expressways": "/ɛkspɹˈɛswe‍ɪz/",
    "expropriated": "/ɛkspɹˈɒpɹɪətɪd/",
    "expropriate": "/ɛkspɹˈɒpɹɪət/",
    "expropriating": "/ɛkspɹˈɒpɹɪətɪŋ/",
    "expropriation": "/ɛkspɹˌɒpɹɪˈe‍ɪʃən/",
    "expropriators": "/ɛkspɹˈɒpɹɪˌe‍ɪtəz/",
    "expulsion": "/ɛkspˈʌlʃən/",
    "expulsions": "/ɛkspˈʌlʃənz/",
    "expunged": "/ɛkspˈʌnd‍ʒd/",
    "expunge": "/ɛkspˈʌnd‍ʒ/",
    "expunges": "/ɛkspˈʌnd‍ʒɪz/",
    "expurgated": "/ɛkspˈɜːɡe‍ɪtɪd/",
    "exquisite": "/ɛkskwˈɪsɪt/",
    "exquisitely": "/ɛkskwˈɪsɪtli/",
    "exquisiteness": "/ɛkskwˈɪsɪtnəs/",
    "extant": "/ɛkstˈɑːnt/",
    "extemporaneous": "/ɛkstˌɛmpɔːɹˈe‍ɪni‍əs/",
    "extempore": "/ɛkstˈɛmpɔː/",
    "extemporise": "/ɛkstˈɛmpɔːɹˌa‍ɪz/",
    "extendable": "/ɛkstˈɛndəbə‍l/",
    "extended": "/ɛkstˈɛndɪd/",
    "extend": "/ɛkstˈɛnd/",
    "extender": "/ɛkstˈɛndɐ/",
    "extending": "/ɛkstˈɛndɪŋ/",
    "extends": "/ɛkstˈɛndz/",
    "extensible": "/ɛkstˈɛnsəbə‍l/",
    "extension": "/ɛkstˈɛnʃən/",
    "extensions": "/ɛkstˈɛnʃənz/",
    "extensive": "/ɛkstˈɛnsɪv/",
    "extensively": "/ɛkstˈɛnsɪvli/",
    "extensor": "/ɛkstˈɛnsɐ/",
    "extent": "/ɛkstˈɛnt/",
    "extents": "/ɛkstˈɛnts/",
    "extenuated": "/ɛkstˈɛnjuːˌe‍ɪtɪd/",
    "extenuating": "/ɛkstˈɛnjuːˌe‍ɪtɪŋ/",
    "exterior": "/ɛkstˈi‍əɹɪɐ/",
    "exteriors": "/ɛkstˈi‍əɹɪəz/",
    "exterminated": "/ɛkstˈɜːmɪnˌe‍ɪtɪd/",
    "exterminate": "/ɛkstˈɜːmɪnˌe‍ɪt/",
    "exterminating": "/ɛkstˈɜːmɪnˌe‍ɪtɪŋ/",
    "extermination": "/ɛkstˈɜːmɪnˈe‍ɪʃən/",
    "exterminator": "/ɛkstˈɜːmɪnˌe‍ɪtɐ/",
    "exterminators": "/ɛkstˈɜːmɪnˌe‍ɪtəz/",
    "external": "/ɛkstˈɜːnə‍l/",
    "externalised": "/ɛkstˈɜːnəlˌa‍ɪzd/",
    "externalise": "/ɛkstˈɜːnəlˌa‍ɪz/",
    "externalities": "/ɛkstˈɜːnˈælɪtiz/",
    "externally": "/ɛkstˈɜːnə‍li/",
    "externals": "/ɛkstˈɜːnə‍lz/",
    "extinct": "/ɛkstˈɪŋkt/",
    "extinction": "/ɛkstˈɪŋkʃən/",
    "extinctions": "/ɛkstˈɪŋkʃənz/",
    "extinguished": "/ɛkstˈɪŋɡwɪʃt/",
    "extinguish": "/ɛkstˈɪŋɡwɪʃ/",
    "extinguisher": "/ɛkstˈɪŋɡwɪʃɐ/",
    "extinguishers": "/ɛkstˈɪŋɡwɪʃəz/",
    "extinguishes": "/ɛkstˈɪŋɡwɪʃɪz/",
    "extinguishing": "/ɛkstˈɪŋɡwɪʃɪŋ/",
    "extirpated": "/ɛkstˈɜːpe‍ɪtɪd/",
    "extirpate": "/ɛkstˈɜːpe‍ɪt/",
    "extirpation": "/ɛkstəpˈe‍ɪʃən/",
    "extol": "/ɛkstˈə‍ʊl/",
    "extolled": "/ɛkstˈə‍ʊld/",
    "extolling": "/ɛkstˈə‍ʊlɪŋ/",
    "extols": "/ɛkstˈə‍ʊlz/",
    "extorted": "/ɛkstˈɔːtɪd/",
    "extort": "/ɛkstˈɔːt/",
    "extorting": "/ɛkstˈɔːtɪŋ/",
    "extortionate": "/ɛkstˈɔːʃənət/",
    "extortionately": "/ɛkstˈɔːʃənətli/",
    "extortion": "/ɛkstˈɔːʃən/",
    "extortionist": "/ɛkstˈɔːʃənˌɪst/",
    "extorts": "/ɛkstˈɔːts/",
    "extracellular": "/ˌɛkstɹəsˈɛljʊlɐ/",
    "extractable": "/ɛkstɹˈæktəbə‍l/",
    "extracted": "/ɛkstɹˈæktɪd/",
    "extracting": "/ɛkstɹˈæktɪŋ/",
    "extraction": "/ɛkstɹˈækʃən/",
    "extractions": "/ɛkstɹˈækʃənz/",
    "extractive": "/ɛkstɹˈæktɪv/",
    "extractor": "/ˈɛkstɹæktɐ/",
    "extractors": "/ˈɛkstɹæktəz/",
    "extracurricular": "/ˌɛkstɹəkəɹˈɪkjʊlɐ/",
    "extradited": "/ˈɛkstɹədˌa‍ɪtɪd/",
    "extradite": "/ˈɛkstɹədˌa‍ɪt/",
    "extraditing": "/ˈɛkstɹədˌa‍ɪtɪŋ/",
    "extradition": "/ˌɛkstɹədˈɪʃən/",
    "extraditions": "/ˌɛkstɹədˈɪʃənz/",
    "extra": "/ˈɛkstɹɐ/",
    "extramarital": "/ˈɛkstɹəmˌæɹɪtə‍l/",
    "extraneous": "/ɛkstɹˈe‍ɪni‍əs/",
    "extraordinaire": "/ɛkstɹˌɔːdɪnˈe‍ə/",
    "extraordinarily": "/ɛkstɹˌɔːdɪnˈɛɹəli/",
    "extraordinary": "/ɛkstɹˈɔːdɪnəɹi/",
    "extrapolated": "/ɛkstɹˈæpəlˌe‍ɪtɪd/",
    "extrapolate": "/ɛkstɹˈæpəlˌe‍ɪt/",
    "extrapolating": "/ɛkstɹˈæpəlˌe‍ɪtɪŋ/",
    "extrapolation": "/ɛkstɹˈæpəlˈe‍ɪʃən/",
    "extrapolations": "/ɛkstɹˈæpəlˈe‍ɪʃənz/",
    "extrapolator": "/ɛkstɹˈæpəlˌe‍ɪtɐ/",
    "extras": "/ˈɛkstɹəz/",
    "extrasolar": "/ˌɛkstɹəsˈə‍ʊlɐ/",
    "extraterrestrial": "/ˌɛkstɹətəɹˈɛstɹɪəl/",
    "extraterrestrials": "/ˌɛkstɹətəɹˈɛstɹɪəlz/",
    "extravagance": "/ɛkstɹˈævəɡəns/",
    "extravagances": "/ɛkstɹˈævəɡənsɪz/",
    "extravagant": "/ɛkstɹˈævəɡənt/",
    "extravagantly": "/ɛkstɹˈævəɡəntli/",
    "extravaganza": "/ɛkstɹˌævəɡˈænzɐ/",
    "extravaganzas": "/ɛkstɹˌævəɡˈænzəz/",
    "extraversion": "/ˌɛkstɹəvˈɜːʃən/",
    "extreme": "/ɛkstɹˈiːm/",
    "extremely": "/ɛkstɹˈiːmli/",
    "extremeness": "/ɛkstɹˈiːmnəs/",
    "extremes": "/ɛkstɹˈiːmz/",
    "extremest": "/ɛkstɹˈɛməst/",
    "extremism": "/ɛkstɹˈiːmɪzəm/",
    "extremist": "/ɛkstɹˈiːmɪst/",
    "extremists": "/ɛkstɹˈiːmɪsts/",
    "extremities": "/ɛkstɹˈɛmɪtiz/",
    "extremity": "/ɛkstɹˈɛmɪti/",
    "extricable": "/ɛkstɹˈɪkəbə‍l/",
    "extricated": "/ˈɛkstɹɪkˌe‍ɪtɪd/",
    "extricate": "/ˈɛkstɹɪkˌe‍ɪt/",
    "extricating": "/ˈɛkstɹɪkˌe‍ɪtɪŋ/",
    "extrication": "/ɛkstɹɪkˈe‍ɪʃən/",
    "extrinsic": "/ɛkstɹˈɪnzɪk/",
    "extroversion": "/ˌɛkstɹəvˈɜːʃən/",
    "extroverted": "/ˈɛkstɹəvˌɜːtɪd/",
    "extrovert": "/ˈɛkstɹəvˌɜːt/",
    "extroverts": "/ˈɛkstɹəvˌɜːts/",
    "extruded": "/ɛkstɹˈuːdɪd/",
    "extrude": "/ɛkstɹˈuːd/",
    "extruder": "/ɛkstɹˈuːdɐ/",
    "extrusion": "/ɛkstɹˈuːʒən/",
    "extrusions": "/ɛkstɹˈuːʒənz/",
    "exuberance": "/ɛɡzjˈuːbəɹəns/",
    "exuberant": "/ɛɡzjˈuːbəɹənt/",
    "exuberantly": "/ɛɡzjˈuːbəɹəntli/",
    "exuded": "/ɛɡzjˈuːdɪd/",
    "exude": "/ɛɡzjˈuːd/",
    "exudes": "/ɛɡzjˈuːdz/",
    "exuding": "/ɛɡzjˈuːdɪŋ/",
    "exultant": "/ɛɡzˈʌltənt/",
    "exultantly": "/ɛɡzˈʌltəntli/",
    "exultation": "/ɛɡzəltˈe‍ɪʃən/",
    "exulted": "/ɛɡzˈʌltɪd/",
    "exult": "/ɛɡzˈʌlt/",
    "eye": "/ˈa‍ɪ/",
    "eyeball": "/ˈa‍ɪbɔːl/",
    "eyeballed": "/ˈa‍ɪbə‍ld/",
    "eyeballing": "/ˈa‍ɪbɔːlɪŋ/",
    "eyeballs": "/ˈa‍ɪbɔːlz/",
    "eyebright": "/ˈa‍ɪbɹa‍ɪt/",
    "eyebrow": "/ˈa‍ɪbɹa‍ʊ/",
    "eyebrows": "/ˈa‍ɪbɹa‍ʊz/",
    "eyed": "/ˈa‍ɪd/",
    "eyeful": "/ˈa‍ɪfə‍l/",
    "eyefuls": "/ˈa‍ɪfə‍lz/",
    "eyeglass": "/ˈa‍ɪɡlɑːs/",
    "eyeglasses": "/ˈa‍ɪɡlɑːsɪz/",
    "eyeing": "/ˈa‍ɪɪŋ/",
    "eyelash": "/ˈa‍ɪlæʃ/",
    "eyelashes": "/ˈa‍ɪlæʃɪz/",
    "eyeless": "/ˈa‍ɪləs/",
    "eyelet": "/ˈa‍ɪlət/",
    "eyelets": "/ˈa‍ɪləts/",
    "eyelid": "/ˈa‍ɪlɪd/",
    "eyelids": "/ˈa‍ɪlɪdz/",
    "eyeliner": "/ˈa‍ɪla‍ɪnɐ/",
    "eyepiece": "/ˈa‍ɪpiːs/",
    "eyepieces": "/ˈa‍ɪpiːsɪz/",
    "eyes": "/ˈa‍ɪz/",
    "eyeshadow": "/ˈa‍ɪʃɐdˌə‍ʊ/",
    "eyeshot": "/ˈa‍ɪʃɒt/",
    "eyesight": "/ˈa‍ɪsa‍ɪt/",
    "eyesore": "/ˈa‍ɪsɔː/",
    "eyesores": "/ˈa‍ɪsɔːz/",
    "eyespot": "/ˈa‍ɪspɒt/",
    "eyespots": "/ˈa‍ɪspɒts/",
    "eyestalk": "/ˈa‍ɪstɔːk/",
    "eyestrain": "/ˈa‍ɪstɹe‍ɪn/",
    "eyeteeth": "/ˈa‍ɪtiːθ/",
    "eyetooth": "/ˈa‍ɪtuːθ/",
    "eyewash": "/ˈa‍ɪwɒʃ/",
    "eyewitness": "/ˈa‍ɪwɪtnəs/",
    "eyewitnesses": "/ˈa‍ɪwɪtnəsɪz/",
    "eying": "/ˈa‍ɪɪŋ/",
    "eyre": "/ˈa‍ɪɐ/",
    "eyrie": "/ˈi‍əɹi/"
}